Workbook

Sheet INDEX
A1: TABLE DF(I,J,K,C,T) demanda
A2: TABLE CF(I,J,K) custo de mover cheio
A3: PARAMETER CE(I,J,K) custo de mover vazio
A4: PARAMETER CS(K) custo estoque;
A5: PARAMETER CM(C) custo tipo de carga;
A6: PARAMETER CR(I,K) custo de reparo;
A7: TABLE CO(I,K,T) custo inserção conteiner no sistema
A8: TABLE RF(I,J,K,C,T) revenue
A9: TABLE O(I,K,T) disponibilidade de conteineres vazios
A10: TABLE E0(I,K) estoque inicial
A11: TABLE WF(C,K) peso conteiner cheio
A12: PARAMETER WE(K) peso conteiner vazio
... A25: PARAMETER NE(I) capacidade maxima de estoque

Sheet DE-PARA
A1: De | B1: Para | D1: De | E1: Para | G1: De | H1: Para | J1: De | K1: Para | M1: De | N1: Para | P1: De | Q1: Para
A2: MAO | B2: 1 | D2: =ROTA!A2 -> NB_PNG | E2: 1 | F2: high cube | G2: K40_D | H2: 1 | J2: C_01 | K2: 1 | M2: T_01 | N2: 1 | P2: DT_0 | Q2: 1
A3: PEC | B3: 2 | D3: =ROTA!A3 -> NB_SSZ | E3: =E2+1 -> 2 | F3: reefer high | G3: K40_R | H3: 2 | J3: C_02 | K3: 2 | M3: T_02 | N3: 2 | P3: DT_1 | Q3: 2
A4: SUA | B4: 3 | D4: =ROTA!A4 -> NB_SUA | E4: =E3+1 -> 3 | F4: dry std | G4: K20_D | H4: 3 | M4: T_03 | N4: 3 | P4: DT_2 | Q4: 3
A5: SSA | B5: 4 | D5: =ROTA!A5 -> NB_PEC | E5: =E4+1 -> 4 | F5: 20 reefer | G5: K20_R | H5: 4 | M5: T_04 | N5: 4 | P5: DT_3 | Q5: 4
A6: IGI | B6: 5 | D6: =ROTA!A6 -> NB_MAO | E6: =E5+1 -> 5 | M6: T_05 | N6: 5
A7: SSZ | B7: 6 | D7: =ROTA!A7 -> SB_MAO | E7: =E6+1 -> 6 | M7: T_06 | N7: 6
A8: IOA | B8: 7 | D8: =ROTA!A8 -> SB_PEC | E8: =E7+1 -> 7 | M8: T_07 | N8: 7
A9: PNG | B9: 8 | D9: =ROTA!A9 -> SB_SUA | E9: =E8+1 -> 8 | M9: T_08 | N9: 8
A10: ITJ | B10: 9 | D10: =ROTA!A10 -> SB_SSZ | E10: =E9+1 -> 9 | M10: T_09 | N10: 9
A11: VLC | B11: 10 | D11: =ROTA!A11 -> SB_PNG | E11: =E10+1 -> 10 | M11: T_10 | N11: 10
A12: SLZ | B12: 11 | M12: T_11 | N12: 11
A13: VIX | B13: 12 | M13: T_12 | N13: 12
A14: RIO | B14: 13
A15: NVT | B15: 14
A16: IBI | B16: 15
A17: RIG | B17: 16

Sheet ROTA
A1: Porto | B1: IdPorto
A2: NB_PNG | B2: 8
A3: NB_SSZ | B3: 6
A4: NB_SUA | B4: 3
A5: NB_PEC | B5: 2
A6: NB_MAO | B6: 1
A7: SB_MAO | B7: 1
A8: SB_PEC | B8: 2
A9: SB_SUA | B9: 3
A10: SB_SSZ | B10: 6
A11: SB_PNG | B11: 8
C16: =SUBSTITUTE(A16,"NB_", "SB_")
C17: =SUBSTITUTE(A17,"NB_", "SB_")
C18: =SUBSTITUTE(A18,"NB_", "SB_")

Sheet PAR CF
A1: Coluna1 | B1: Coluna2 | C1: K20_D | D1: K20_R | E1: K40_D | F1: K40_R | H1: I | I1: J | J1: K | K1: CF
A2: I_MAO. | B2: J_MAO | C2: 1440 | D2: 2440 | E2: 1440 | F2: 2440 | H2: 1 | I2: 1 | J2: 3 | K2: 1440
A3: I_MAO. | B3: J_PEC | C3: 1450 | D3: 2122 | E3: 1450 | F3: 2122 | H3: 1 | I3: 1 | J3: 4 | K3: 2440
A4: I_MAO. | B4: J_SUA | C4: 1820 | D4: 2632 | E4: 1820 | F4: 2632 | H4: 1 | I4: 1 | J4: 1 | K4: 1440
A5: I_MAO. | B5: J_SSA | C5: 1770 | D5: 2728 | E5: 1770 | F5: 2728 | H5: 1 | I5: 1 | J5: 2 | K5: 2440
A6: I_MAO. | B6: J_IGI | C6: 1290 | D6: 2124 | E6: 1290 | F6: 2124 | H6: 1 | I6: 2 | J6: 3 | K6: 1450
A7: I_MAO. | B7: J_SSZ | C7: 1420 | D7: 2212 | E7: 1420 | F7: 2212 | H7: 1 | I7: 2 | J7: 4 | K7: 2122
A8: I_MAO. | B8: J_PNG | C8: 1660 | D8: 2450 | E8: 1660 | F8: 2450 | H8: 1 | I8: 2 | J8: 1 | K8: 1450
A9: I_MAO. | B9: J_IOA | C9: 1330 | D9: 1990 | E9: 1330 | F9: 1990 | H9: 1 | I9: 2 | J9: 2 | K9: 2122
A10: I_PEC. | B10: J_MAO | C10: 1450 | D10: 2122 | E10: 1450 | F10: 2122 | H10: 1 | I10: 3 | J10: 3 | K10: 1820
A11: I_PEC. | B11: J_PEC | C11: 1460 | D11: 1804 | E11: 1460 | F11: 1804 | H11: 1 | I11: 3 | J11: 4 | K11: 2632
A12: I_PEC. | B12: J_SUA | C12: 1830 | D12: 2314 | E12: 1830 | F12: 2314 | H12: 1 | I12: 3 | J12: 1 | K12: 1820
A13: I_PEC. | B13: J_SSA | C13: 1780 | D13: 2410 | E13: 1780 | F13: 2410 | H13: 1 | I13: 3 | J13: 2 | K13: 2632
... A65: I_IOA. | B65: J_IOA | C65: 1220 | D65: 1540 | E65: 1220 | F65: 1540 | H65: 2 | I65: 7 | J65: 2 | K65: 1672
H66: 3 | I66: 1 | J66: 3 | K66: 1820
H67: 3 | I67: 1 | J67: 4 | K67: 2632
H68: 3 | I68: 1 | J68: 1 | K68: 1820
H69: 3 | I69: 1 | J69: 2 | K69: 2632
H70: 3 | I70: 2 | J70: 3 | K70: 1830
H71: 3 | I71: 2 | J71: 4 | K71: 2314
H72: 3 | I72: 2 | J72: 1 | K72: 1830
H73: 3 | I73: 2 | J73: 2 | K73: 2314
H74: 3 | I74: 3 | J74: 3 | K74: 2200
H75: 3 | I75: 3 | J75: 4 | K75: 2824
H76: 3 | I76: 3 | J76: 1 | K76: 2200
H77: 3 | I77: 3 | J77: 2 | K77: 2824
... H257: 7 | I257: 7 | J257: 2 | K257: 1540

Sheet PAR CE
A1: Coluna1 | B1: Coluna2 | C1: K20_D | D1: K20_R | E1: K40_D | F1: K40_R | H1: I | I1: J | J1: K | K1: CE
A2: I_MAO. | B2: J_MAO | C2: 1200 | D2: 1200 | E2: 1200 | F2: 1200 | H2: 1 | I2: 1 | J2: 3 | K2: 1200 | M2: 1200
A3: I_MAO. | B3: J_PEC | C3: 1205 | D3: 1205 | E3: 1205 | F3: 1205 | H3: 1 | I3: 1 | J3: 4 | K3: 1200 | M3: 1200
A4: I_MAO. | B4: J_SUA | C4: 1390 | D4: 1390 | E4: 1390 | F4: 1390 | H4: 1 | I4: 1 | J4: 1 | K4: 1200 | M4: 1200
A5: I_MAO. | B5: J_SSA | C5: 1365 | D5: 1365 | E5: 1365 | F5: 1365 | H5: 1 | I5: 1 | J5: 2 | K5: 1200 | M5: 1200
A6: I_MAO. | B6: J_IGI | C6: 1125 | D6: 1125 | E6: 1125 | F6: 1125 | H6: 1 | I6: 2 | J6: 3 | K6: 1205 | M6: 1205
A7: I_MAO. | B7: J_SSZ | C7: 1190 | D7: 1190 | E7: 1190 | F7: 1190 | H7: 1 | I7: 2 | J7: 4 | K7: 1205 | M7: 1205
A8: I_MAO. | B8: J_PNG | C8: 1310 | D8: 1310 | E8: 1310 | F8: 1310 | H8: 1 | I8: 2 | J8: 1 | K8: 1205 | M8: 1205
A9: I_MAO. | B9: J_IOA | C9: 1145 | D9: 1145 | E9: 1145 | F9: 1145 | H9: 1 | I9: 2 | J9: 2 | K9: 1205 | M9: 1205
A10: I_PEC. | B10: J_MAO | C10: 1205 | D10: 1205 | E10: 1205 | F10: 1205 | H10: 1 | I10: 3 | J10: 3 | K10: 1390 | M10: 1390
A11: I_PEC. | B11: J_PEC | C11: 1210 | D11: 1210 | E11: 1210 | F11: 1210 | H11: 1 | I11: 3 | J11: 4 | K11: 1390 | M11: 1390
A12: I_PEC. | B12: J_SUA | C12: 1395 | D12: 1395 | E12: 1395 | F12: 1395 | H12: 1 | I12: 3 | J12: 1 | K12: 1390 | M12: 1390
A13: I_PEC. | B13: J_SSA | C13: 1370 | D13: 1370 | E13: 1370 | F13: 1370 | H13: 1 | I13: 3 | J13: 2 | K13: 1390 | M13: 1390
... A65: I_IOA. | B65: J_IOA | C65: 1090 | D65: 1090 | E65: 1090 | F65: 1090 | H65: 2 | I65: 7 | J65: 2 | K65: 1150 | M65: 1150
H66: 3 | I66: 1 | J66: 3 | K66: 1390 | M66: 1390
H67: 3 | I67: 1 | J67: 4 | K67: 1390 | M67: 1390
H68: 3 | I68: 1 | J68: 1 | K68: 1390 | M68: 1390
H69: 3 | I69: 1 | J69: 2 | K69: 1390 | M69: 1390
H70: 3 | I70: 2 | J70: 3 | K70: 1395 | M70: 1395
H71: 3 | I71: 2 | J71: 4 | K71: 1395 | M71: 1395
H72: 3 | I72: 2 | J72: 1 | K72: 1395 | M72: 1395
H73: 3 | I73: 2 | J73: 2 | K73: 1395 | M73: 1395
H74: 3 | I74: 3 | J74: 3 | K74: 1580 | M74: 1580
H75: 3 | I75: 3 | J75: 4 | K75: 1580 | M75: 1580
H76: 3 | I76: 3 | J76: 1 | K76: 1580 | M76: 1580
H77: 3 | I77: 3 | J77: 2 | K77: 1580 | M77: 1580
... H257: 7 | I257: 7 | J257: 2 | K257: 1090 | M257: 1090

Sheet PAR CS
A1: CS('K20_D')= | B1: 2 | C1: ; | D1: K | E1: CS
A2: CS('K20_R')= | B2: 2 | C2: ; | D2: 3 | E2: 2
A3: CS('K40_D')= | B3: 2 | C3: ; | D3: 4 | E3: 2
A4: CS('K40_R')= | B4: 2 | C4: ; | D4: 1 | E4: 2
D5: 2 | E5: 2
A7: =LEFT(RIGHT(A1,8),5) -> K20_D
A8: =LEFT(RIGHT(A2,8),5) -> K20_R
A9: =LEFT(RIGHT(A3,8),5) -> K40_D
A10: =LEFT(RIGHT(A4,8),5) -> K40_R
A11: =LEFT(RIGHT(A5,8),5)

Sheet PAR CR
A1: Coluna1 | B1: K20_D | C1: K20_R | D1: K40_D | E1: K40_R | G1: I | H1: K | I1: CR
A2: I_MAO | G2: 1 | H2: 3 | I2: 0
A3: I_PEC | G3: 1 | H3: 4 | I3: 0
A4: I_SUA | G4: 1 | H4: 1 | I4: 0
A5: I_SSA | G5: 1 | H5: 2 | I5: 0
A6: I_IGI | G6: 2 | H6: 3 | I6: 0
A7: I_SSZ | G7: 2 | H7: 4 | I7: 0
A8: I_PNG | G8: 2 | H8: 1 | I8: 0
A9: I_IOA | G9: 2 | H9: 2 | I9: 0
G10: 3 | H10: 3 | I10: 0
G11: 3 | H11: 4 | I11: 0
G12: 3 | H12: 1 | I12: 0
G13: 3 | H13: 2 | I13: 0
G14: 4 | H14: 3 | I14: 0
G15: 4 | H15: 4 | I15: 0
G16: 4 | H16: 1 | I16: 0
G17: 4 | H17: 2 | I17: 0
G18: 5 | H18: 3 | I18: 0
G19: 5 | H19: 4 | I19: 0
G20: 5 | H20: 1 | I20: 0
G21: 5 | H21: 2 | I21: 0
... G33: 8 | H33: 2 | I33: 0

Sheet PAR CM
A1: CM('C_01')= | B1: 0 | C1: ; | D1: C | E1: CM
A2: CM('C_02')= | B2: 0 | C2: ; | D2: 1 | E2: 0
D3: 2 | E3: 0

Sheet PAR CV
A1: NT | B1: CV
A2: 3500 | B2: 25000
A3: 3000 | B3: 21000
A4: 2500 | B4: 18000
A5: 2000 | B5: 15000

Sheet PAR DF
A1: Coluna1 | B1: Coluna2 | C1: Coluna3 | D1: Coluna4 | E1: T_01 | F1: T_02 | G1: T_03 | H1: T_04 | I1: T_05 | J1: T_06 | K1: T_07 | L1: T_08 | M1: T_09 | N1: T_10 | O1: T_11 | P1: T_12 | R1: I | S1: J | T1: K | U1: T | V1: DF
A2: I_MAO. | B2: J_PEC. | C2: K20_D. | D2: C_01 | E2: 122 | F2: 84 | G2: 130 | H2: 105 | I2: 102 | J2: 115 | K2: 385 | L2: 289 | M2: 277 | N2: 347 | O2: 336 | P2: 190 | R2: 1 | S2: 2 | T2: 3 | U2: 1 | V2: 122
A3: I_MAO. | B3: J_PEC. | C3: K40_D. | D3: C_01 | E3: 241 | F3: 193 | G3: 248 | H3: 209 | I3: 115 | J3: 143 | K3: 261 | L3: 184 | M3: 144 | N3: 152 | O3: 143 | P3: 195 | R3: 1 | S3: 2 | T3: 3 | U3: 2 | V3: 84
A4: I_MAO. | B4: J_PEC. | C4: K40_R. | D4: C_02 | E4: 6 | F4: 1 | G4: 5 | H4: 2 | I4: 4 | J4: 4 | K4: 4 | L4: 2 | M4: 0 | N4: 0 | O4: 2 | P4: 1 | R4: 1 | S4: 2 | T4: 3 | U4: 3 | V4: 130
A5: I_MAO. | B5: J_SUA. | C5: K20_D. | D5: C_01 | E5: 16 | F5: 46 | G5: 25 | H5: 66 | I5: 40 | J5: 38 | K5: 101 | L5: 40 | M5: 35 | N5: 22 | O5: 38 | P5: 42 | R5: 1 | S5: 2 | T5: 3 | U5: 4 | V5: 105
A6: I_MAO. | B6: J_SUA. | C6: K40_D. | D6: C_01 | E6: 1153 | F6: 1453 | G6: 1134 | H6: 1077 | I6: 581 | J6: 892 | K6: 788 | L6: 1298 | M6: 451 | N6: 863 | O6: 722 | P6: 797 | R6: 1 | S6: 2 | T6: 3 | U6: 5 | V6: 102
A7: I_MAO. | B7: J_SUA. | C7: K40_R. | D7: C_02 | E7: 14 | F7: 18 | G7: 22 | H7: 40 | I7: 0 | J7: 56 | K7: 6 | L7: 13 | M7: 7 | N7: 5 | O7: 10 | P7: 9 | R7: 1 | S7: 2 | T7: 3 | U7: 6 | V7: 115
A8: I_MAO. | B8: J_SSA. | C8: K20_D. | D8: C_01 | E8: 0 | F8: 0 | G8: 0 | H8: 0 | I8: 0 | J8: 0 | K8: 0 | L8: 0 | M8: 0 | N8: 0 | O8: 0 | P8: 0 | R8: 1 | S8: 2 | T8: 3 | U8: 7 | V8: 385
A9: I_MAO. | B9: J_SSA. | C9: K40_D. | D9: C_01 | E9: 0 | F9: 0 | G9: 0 | H9: 0 | I9: 0 | J9: 0 | K9: 0 | L9: 0 | M9: 0 | N9: 0 | O9: 0 | P9: 0 | R9: 1 | S9: 2 | T9: 3 | U9: 8 | V9: 289
A10: I_MAO. | B10: J_IGI. | C10: K20_D. | D10: C_01 | E10: 0 | F10: 0 | G10: 0 | H10: 0 | I10: 0 | J10: 0 | K10: 0 | L10: 0 | M10: 0 | N10: 0 | O10: 0 | P10: 0 | R10: 1 | S10: 2 | T10: 3 | U10: 9 | V10: 277
A11: I_MAO. | B11: J_IGI. | C11: K40_D. | D11: C_01 | E11: 0 | F11: 0 | G11: 0 | H11: 0 | I11: 0 | J11: 0 | K11: 0 | L11: 0 | M11: 0 | N11: 0 | O11: 0 | P11: 0 | R11: 1 | S11: 2 | T11: 3 | U11: 10 | V11: 347
A12: I_MAO. | B12: J_IGI. | C12: K40_R. | D12: C_02 | E12: 0 | F12: 0 | G12: 0 | H12: 0 | I12: 0 | J12: 0 | K12: 0 | L12: 0 | M12: 0 | N12: 0 | O12: 0 | P12: 0 | R12: 1 | S12: 2 | T12: 3 | U12: 11 | V12: 336
A13: I_MAO. | B13: J_SSZ. | C13: K20_D. | D13: C_01 | E13: 144 | F13: 144 | G13: 186 | H13: 168 | I13: 170 | J13: 192 | K13: 184 | L13: 200 | M13: 64 | N13: 260 | O13: 252 | P13: 278 | R13: 1 | S13: 2 | T13: 3 | U13: 12 | V13: 190
... A188: I_SSZ. | B188: J_PNG. | C188: K40_R. | D188: C_02 | E188: 0 | F188: 0 | G188: 0 | H188: 0 | I188: 0 | J188: 0 | K188: 0 | L188: 0 | M188: 0 | N188: 0 | O188: 0 | P188: 0 | R188: 1 | S188: 7 | T188: 3 | U188: 7 | V188: 0
R189: 1 | S189: 7 | T189: 3 | U189: 8 | V189: 0
R190: 1 | S190: 7 | T190: 3 | U190: 9 | V190: 0
R191: 1 | S191: 7 | T191: 3 | U191: 10 | V191: 0
R192: 1 | S192: 7 | T192: 3 | U192: 11 | V192: 0
R193: 1 | S193: 7 | T193: 3 | U193: 12 | V193: 0
R194: 1 | S194: 7 | T194: 1 | U194: 1 | V194: 0
R195: 1 | S195: 7 | T195: 1 | U195: 2 | V195: 0
R196: 1 | S196: 7 | T196: 1 | U196: 3 | V196: 0
R197: 1 | S197: 7 | T197: 1 | U197: 4 | V197: 0
R198: 1 | S198: 7 | T198: 1 | U198: 5 | V198: 0
R199: 1 | S199: 7 | T199: 1 | U199: 6 | V199: 0
R200: 1 | S200: 7 | T200: 1 | U200: 7 | V200: 0
... R2245: 8 | S2245: 8 | T2245: 2 | U2245: 12 | V2245: 0

Sheet PAR FEEDER
A1: I | B1: J | C1: PERCENT_FEEDER
A2: 2 | B2: 1 | C2: 0.1117
A3: 2 | B3: 8 | C3: 0.464
A4: 2 | B4: 9 | C4: 0.3271
A5: 2 | B5: 9 | C5: 0.1096
A6: 1 | B6: 2 | C6: 0.002
A7: 1 | B7: 8 | C7: 0
A8: 1 | B8: 9 | C8: 0.0113
A9: 1 | B9: 9 | C9: 0.0007
A10: 8 | B10: 2 | C10: 0.3926
A11: 8 | B11: 1 | C11: 0
A12: 8 | B12: 9 | C12: 0.9955
A13: 8 | B13: 9 | C13: 0.6581
... A21: 9 | B21: 9 | C21: 0.3616

Sheet PAR RF
A1: Coluna1 | B1: Coluna2 | C1: Coluna3 | D1: Coluna4 | E1: T_01 | F1: T_02 | G1: T_03 | H1: T_04 | I1: T_05 | J1: T_06 | K1: T_07 | L1: T_08 | M1: T_09 | N1: T_10 | O1: T_11 | P1: T_12 | R1: I | S1: J | T1: K | U1: C | V1: T | W1: RF | X1: RF Original | Y1: X | AA1: I | AB1: J | AC1: K | AD1: C | AE1: T | AF1: RF | AG1: RF Original
A2: I_IGI. | B2: J_IOA. | C2: K20_D. | D2: C_01 | E2: 1980 | F2: 1980 | G2: 1980 | H2: 1980 | I2: 1980 | J2: 1980 | K2: 1980 | L2: 1980 | M2: 1980 | N2: 1980 | O2: 1980 | P2: 1980 | R2: 6 | S2: 1 | T2: 2 | U2: 2 | V2: 1 | W2: 19103.78 | X2: 13930 | AA2: 6 | AB2: 1 | AC2: 2 | AD2: 2 | AE2: 1 | AF2: 19103.78 | AG2: 13930
A3: I_IGI. | B3: J_IOA. | C3: K20_R. | D3: C_02 | E3: 2900 | F3: 2900 | G3: 2900 | H3: 2900 | I3: 2900 | J3: 2900 | K3: 2900 | L3: 2900 | M3: 2900 | N3: 2900 | O3: 2900 | P3: 2900 | R3: 6 | S3: 1 | T3: 2 | U3: 2 | V3: 2 | W3: 19103.78 | X3: 13930 | AA3: 6 | AB3: 1 | AC3: 2 | AD3: 2 | AE3: 2 | AF3: 19103.78 | AG3: 13930
A4: I_IGI. | B4: J_IOA. | C4: K40_D. | D4: C_01 | E4: 2640 | F4: 2640 | G4: 2640 | H4: 2640 | I4: 2640 | J4: 2640 | K4: 2640 | L4: 2640 | M4: 2640 | N4: 2640 | O4: 2640 | P4: 2640 | R4: 6 | S4: 1 | T4: 2 | U4: 2 | V4: 3 | W4: 19103.78 | X4: 13930 | AA4: 6 | AB4: 1 | AC4: 2 | AD4: 2 | AE4: 3 | AF4: 19103.78 | AG4: 13930
A5: I_IGI. | B5: J_IOA. | C5: K40_R. | D5: C_02 | E5: 4840 | F5: 4840 | G5: 4840 | H5: 4840 | I5: 4840 | J5: 4840 | K5: 4840 | L5: 4840 | M5: 4840 | N5: 4840 | O5: 4840 | P5: 4840 | R5: 6 | S5: 1 | T5: 2 | U5: 2 | V5: 4 | W5: 19103.78 | X5: 13930 | AA5: 6 | AB5: 1 | AC5: 2 | AD5: 2 | AE5: 4 | AF5: 19103.78 | AG5: 13930
A6: I_IGI. | B6: J_MAO. | C6: K20_D. | D6: C_01 | E6: 8800 | F6: 8800 | G6: 8800 | H6: 8800 | I6: 8800 | J6: 8800 | K6: 8800 | L6: 8800 | M6: 8800 | N6: 8800 | O6: 8800 | P6: 8800 | R6: 6 | S6: 1 | T6: 2 | U6: 2 | V6: 5 | W6: 19103.78 | X6: 13930 | AA6: 6 | AB6: 1 | AC6: 2 | AD6: 2 | AE6: 5 | AF6: 19103.78 | AG6: 13930
A7: I_IGI. | B7: J_MAO. | C7: K40_D. | D7: C_01 | E7: 9460 | F7: 9460 | G7: 9460 | H7: 9460 | I7: 9460 | J7: 9460 | K7: 9460 | L7: 9460 | M7: 9460 | N7: 9460 | O7: 9460 | P7: 9460 | R7: 6 | S7: 1 | T7: 2 | U7: 2 | V7: 6 | W7: 19103.78 | X7: 13930 | AA7: 6 | AB7: 1 | AC7: 2 | AD7: 2 | AE7: 6 | AF7: 19103.78 | AG7: 13930
A8: I_IGI. | B8: J_MAO. | C8: K40_R. | D8: C_02 | E8: 11660 | F8: 11660 | G8: 11660 | H8: 11660 | I8: 11660 | J8: 11660 | K8: 11660 | L8: 11660 | M8: 11660 | N8: 11660 | O8: 11660 | P8: 11660 | R8: 6 | S8: 1 | T8: 2 | U8: 2 | V8: 7 | W8: 19103.78 | X8: 13930 | AA8: 6 | AB8: 1 | AC8: 2 | AD8: 2 | AE8: 7 | AF8: 19103.78 | AG8: 13930
A9: I_IGI. | B9: J_PEC. | C9: K20_D. | D9: C_01 | E9: 6160 | F9: 6160 | G9: 6160 | H9: 6160 | I9: 6160 | J9: 6160 | K9: 6160 | L9: 6160 | M9: 6160 | N9: 6160 | O9: 6160 | P9: 6160 | R9: 6 | S9: 1 | T9: 2 | U9: 2 | V9: 8 | W9: 19103.78 | X9: 13930 | AA9: 6 | AB9: 1 | AC9: 2 | AD9: 2 | AE9: 8 | AF9: 19103.78 | AG9: 13930
A10: I_IGI. | B10: J_PEC. | C10: K20_R. | D10: C_02 | E10: 4700 | F10: 4700 | G10: 4700 | H10: 4700 | I10: 4700 | J10: 4700 | K10: 4700 | L10: 4700 | M10: 4700 | N10: 4700 | O10: 4700 | P10: 4700 | R10: 6 | S10: 1 | T10: 2 | U10: 2 | V10: 9 | W10: 19103.78 | X10: 13930 | AA10: 6 | AB10: 1 | AC10: 2 | AD10: 2 | AE10: 9 | AF10: 19103.78 | AG10: 13930
A11: I_IGI. | B11: J_PEC. | C11: K40_D. | D11: C_01 | E11: 6820 | F11: 6820 | G11: 6820 | H11: 6820 | I11: 6820 | J11: 6820 | K11: 6820 | L11: 6820 | M11: 6820 | N11: 6820 | O11: 6820 | P11: 6820 | R11: 6 | S11: 1 | T11: 2 | U11: 2 | V11: 10 | W11: 19103.78 | X11: 13930 | AA11: 6 | AB11: 1 | AC11: 2 | AD11: 2 | AE11: 10 | AF11: 19103.78 | AG11: 13930
A12: I_IGI. | B12: J_PEC. | C12: K40_R. | D12: C_02 | E12: 9020 | F12: 9020 | G12: 9020 | H12: 9020 | I12: 9020 | J12: 9020 | K12: 9020 | L12: 9020 | M12: 9020 | N12: 9020 | O12: 9020 | P12: 9020 | R12: 6 | S12: 1 | T12: 2 | U12: 2 | V12: 11 | W12: 19103.78 | X12: 13930 | AA12: 6 | AB12: 1 | AC12: 2 | AD12: 2 | AE12: 11 | AF12: 19103.78 | AG12: 13930
A13: I_IGI. | B13: J_PNG. | C13: K20_D. | D13: C_01 | E13: 1980 | F13: 1980 | G13: 1980 | H13: 1980 | I13: 1980 | J13: 1980 | K13: 1980 | L13: 1980 | M13: 1980 | N13: 1980 | O13: 1980 | P13: 1980 | R13: 6 | S13: 1 | T13: 2 | U13: 2 | V13: 12 | W13: 19103.78 | X13: 13930 | AA13: 6 | AB13: 1 | AC13: 2 | AD13: 2 | AE13: 12 | AF13: 19103.78 | AG13: 13930
A14: I_IGI. | B14: J_PNG. | C14: K20_R. | D14: C_02 | E14: 2900 | F14: 2900 | G14: 2900 | H14: 2900 | I14: 2900 | J14: 2900 | K14: 2900 | L14: 2900 | M14: 2900 | N14: 2900 | O14: 2900 | P14: 2900 | R14: 6 | S14: 1 | T14: 1 | U14: 1 | V14: 1 | W14: 13133.6 | X14: 12935 | Y14: x | AA14: 6 | AB14: 1 | AC14: 1 | AD14: 1 | AE14: 1 | AF14: 13133.6 | AG14: 12935
A15: I_IGI. | B15: J_PNG. | C15: K40_D. | D15: C_01 | E15: 2640 | F15: 2640 | G15: 2640 | H15: 2640 | I15: 2640 | J15: 2640 | K15: 2640 | L15: 2640 | M15: 2640 | N15: 2640 | O15: 2640 | P15: 2640 | R15: 6 | S15: 1 | T15: 1 | U15: 1 | V15: 2 | W15: 13133.6 | X15: 12935 | AA15: 6 | AB15: 1 | AC15: 1 | AD15: 1 | AE15: 2 | AF15: 13133.6 | AG15: 12935
A16: I_IGI. | B16: J_PNG. | C16: K40_R. | D16: C_02 | E16: 4840 | F16: 4840 | G16: 4840 | H16: 4840 | I16: 4840 | J16: 4840 | K16: 4840 | L16: 4840 | M16: 4840 | N16: 4840 | O16: 4840 | P16: 4840 | R16: 6 | S16: 1 | T16: 1 | U16: 1 | V16: 3 | W16: 13133.6 | X16: 12935 | AA16: 6 | AB16: 1 | AC16: 1 | AD16: 1 | AE16: 3 | AF16: 13133.6 | AG16: 12935
A17: I_IGI. | B17: J_SSA. | C17: K20_D. | D17: C_01 | E17: 5940 | F17: 5940 | G17: 5940 | H17: 5940 | I17: 5940 | J17: 5940 | K17: 5940 | L17: 5940 | M17: 5940 | N17: 5940 | O17: 5940 | P17: 5940 | R17: 6 | S17: 1 | T17: 1 | U17: 1 | V17: 4 | W17: 13133.6 | X17: 12935 | AA17: 6 | AB17: 1 | AC17: 1 | AD17: 1 | AE17: 4 | AF17: 13133.6 | AG17: 12935
A18: I_IGI. | B18: J_SSA. | C18: K40_D. | D18: C_01 | E18: 6600 | F18: 6600 | G18: 6600 | H18: 6600 | I18: 6600 | J18: 6600 | K18: 6600 | L18: 6600 | M18: 6600 | N18: 6600 | O18: 6600 | P18: 6600 | R18: 6 | S18: 1 | T18: 1 | U18: 1 | V18: 5 | W18: 13133.6 | X18: 12935 | AA18: 6 | AB18: 1 | AC18: 1 | AD18: 1 | AE18: 5 | AF18: 13133.6 | AG18: 12935
A19: I_IGI. | B19: J_SSA. | C19: K40_R. | D19: C_02 | E19: 8800 | F19: 8800 | G19: 8800 | H19: 8800 | I19: 8800 | J19: 8800 | K19: 8800 | L19: 8800 | M19: 8800 | N19: 8800 | O19: 8800 | P19: 8800 | R19: 6 | S19: 1 | T19: 1 | U19: 1 | V19: 6 | W19: 13133.6 | X19: 12935 | AA19: 6 | AB19: 1 | AC19: 1 | AD19: 1 | AE19: 6 | AF19: 13133.6 | AG19: 12935
A20: I_IGI. | B20: J_SSZ. | C20: K20_D. | D20: C_01 | E20: 2310 | F20: 2310 | G20: 2310 | H20: 2310 | I20: 2310 | J20: 2310 | K20: 2310 | L20: 2310 | M20: 2310 | N20: 2310 | O20: 2310 | P20: 2310 | R20: 6 | S20: 1 | T20: 1 | U20: 1 | V20: 7 | W20: 13133.6 | X20: 12935 | AA20: 6 | AB20: 1 | AC20: 1 | AD20: 1 | AE20: 7 | AF20: 13133.6 | AG20: 12935
A21: I_IGI. | B21: J_SSZ. | C21: K20_R. | D21: C_02 | E21: 3100 | F21: 3100 | G21: 3100 | H21: 3100 | I21: 3100 | J21: 3100 | K21: 3100 | L21: 3100 | M21: 3100 | N21: 3100 | O21: 3100 | P21: 3100 | R21: 6 | S21: 1 | T21: 1 | U21: 1 | V21: 8 | W21: 13133.6 | X21: 12935 | AA21: 6 | AB21: 1 | AC21: 1 | AD21: 1 | AE21: 8 | AF21: 13133.6 | AG21: 12935
A22: I_IGI. | B22: J_SSZ. | C22: K40_D. | D22: C_01 | E22: 2970 | F22: 2970 | G22: 2970 | H22: 2970 | I22: 2970 | J22: 2970 | K22: 2970 | L22: 2970 | M22: 2970 | N22: 2970 | O22: 2970 | P22: 2970 | R22: 6 | S22: 1 | T22: 1 | U22: 1 | V22: 9 | W22: 13133.6 | X22: 12935 | AA22: 6 | AB22: 1 | AC22: 1 | AD22: 1 | AE22: 9 | AF22: 13133.6 | AG22: 12935
A23: I_IGI. | B23: J_SSZ. | C23: K40_R. | D23: C_02 | E23: 5170 | F23: 5170 | G23: 5170 | H23: 5170 | I23: 5170 | J23: 5170 | K23: 5170 | L23: 5170 | M23: 5170 | N23: 5170 | O23: 5170 | P23: 5170 | R23: 6 | S23: 1 | T23: 1 | U23: 1 | V23: 10 | W23: 13133.6 | X23: 12935 | AA23: 6 | AB23: 1 | AC23: 1 | AD23: 1 | AE23: 10 | AF23: 13133.6 | AG23: 12935
A24: I_IGI. | B24: J_SUA. | C24: K20_D. | D24: C_01 | E24: 6270 | F24: 6270 | G24: 6270 | H24: 6270 | I24: 6270 | J24: 6270 | K24: 6270 | L24: 6270 | M24: 6270 | N24: 6270 | O24: 6270 | P24: 6270 | R24: 6 | S24: 1 | T24: 1 | U24: 1 | V24: 11 | W24: 13133.6 | X24: 12935 | AA24: 6 | AB24: 1 | AC24: 1 | AD24: 1 | AE24: 11 | AF24: 13133.6 | AG24: 12935
A25: I_IGI. | B25: J_SUA. | C25: K20_R. | D25: C_02 | E25: 4500 | F25: 4500 | G25: 4500 | H25: 4500 | I25: 4500 | J25: 4500 | K25: 4500 | L25: 4500 | M25: 4500 | N25: 4500 | O25: 4500 | P25: 4500 | R25: 6 | S25: 1 | T25: 1 | U25: 1 | V25: 12 | W25: 13133.6 | X25: 12935 | AA25: 6 | AB25: 1 | AC25: 1 | AD25: 1 | AE25: 12 | AF25: 13133.6 | AG25: 12935
A26: I_IGI. | B26: J_SUA. | C26: K40_D. | D26: C_01 | E26: 6930 | F26: 6930 | G26: 6930 | H26: 6930 | I26: 6930 | J26: 6930 | K26: 6930 | L26: 6930 | M26: 6930 | N26: 6930 | O26: 6930 | P26: 6930 | R26: 8 | S26: 1 | T26: 2 | U26: 2 | V26: 1 | W26: 20214.79 | X26: 12650 | Y26: x | AA26: 8 | AB26: 1 | AC26: 2 | AD26: 2 | AE26: 1 | AF26: 20214.79 | AG26: 12650
A27: I_IGI. | B27: J_SUA. | C27: K40_R. | D27: C_02 | E27: 9130 | F27: 9130 | G27: 9130 | H27: 9130 | I27: 9130 | J27: 9130 | K27: 9130 | L27: 9130 | M27: 9130 | N27: 9130 | O27: 9130 | P27: 9130 | R27: 8 | S27: 1 | T27: 2 | U27: 2 | V27: 2 | W27: 20214.79 | X27: 12650 | AA27: 8 | AB27: 1 | AC27: 2 | AD27: 2 | AE27: 2 | AF27: 20214.79 | AG27: 12650
A28: I_IOA. | B28: J_IGI. | C28: K20_D. | D28: C_01 | E28: 2640 | F28: 2640 | G28: 2640 | H28: 2640 | I28: 2640 | J28: 2640 | K28: 2640 | L28: 2640 | M28: 2640 | N28: 2640 | O28: 2640 | P28: 2640 | R28: 8 | S28: 1 | T28: 2 | U28: 2 | V28: 3 | W28: 20214.79 | X28: 12650 | AA28: 8 | AB28: 1 | AC28: 2 | AD28: 2 | AE28: 3 | AF28: 20214.79 | AG28: 12650
A29: I_IOA. | B29: J_IGI. | C29: K20_R. | D29: C_02 | E29: 3000 | F29: 3000 | G29: 3000 | H29: 3000 | I29: 3000 | J29: 3000 | K29: 3000 | L29: 3000 | M29: 3000 | N29: 3000 | O29: 3000 | P29: 3000 | R29: 8 | S29: 1 | T29: 2 | U29: 2 | V29: 4 | W29: 20214.79 | X29: 12650 | AA29: 8 | AB29: 1 | AC29: 2 | AD29: 2 | AE29: 4 | AF29: 20214.79 | AG29: 12650
A30: I_IOA. | B30: J_IGI. | C30: K40_D. | D30: C_01 | E30: 3300 | F30: 3300 | G30: 3300 | H30: 3300 | I30: 3300 | J30: 3300 | K30: 3300 | L30: 3300 | M30: 3300 | N30: 3300 | O30: 3300 | P30: 3300 | R30: 8 | S30: 1 | T30: 2 | U30: 2 | V30: 5 | W30: 20214.79 | X30: 12650 | AA30: 8 | AB30: 1 | AC30: 2 | AD30: 2 | AE30: 5 | AF30: 20214.79 | AG30: 12650
A31: I_IOA. | B31: J_IGI. | C31: K40_R. | D31: C_02 | E31: 5500 | F31: 5500 | G31: 5500 | H31: 5500 | I31: 5500 | J31: 5500 | K31: 5500 | L31: 5500 | M31: 5500 | N31: 5500 | O31: 5500 | P31: 5500 | R31: 8 | S31: 1 | T31: 2 | U31: 2 | V31: 6 | W31: 20214.79 | X31: 12650 | AA31: 8 | AB31: 1 | AC31: 2 | AD31: 2 | AE31: 6 | AF31: 20214.79 | AG31: 12650
A32: I_IOA. | B32: J_MAO. | C32: K20_D. | D32: C_01 | E32: 8910 | F32: 8910 | G32: 8910 | H32: 8910 | I32: 8910 | J32: 8910 | K32: 8910 | L32: 8910 | M32: 8910 | N32: 8910 | O32: 8910 | P32: 8910 | R32: 8 | S32: 1 | T32: 2 | U32: 2 | V32: 7 | W32: 20214.79 | X32: 12650 | AA32: 8 | AB32: 1 | AC32: 2 | AD32: 2 | AE32: 7 | AF32: 20214.79 | AG32: 12650
A33: I_IOA. | B33: J_MAO. | C33: K40_D. | D33: C_01 | E33: 9570 | F33: 9570 | G33: 9570 | H33: 9570 | I33: 9570 | J33: 9570 | K33: 9570 | L33: 9570 | M33: 9570 | N33: 9570 | O33: 9570 | P33: 9570 | R33: 8 | S33: 1 | T33: 2 | U33: 2 | V33: 8 | W33: 20214.79 | X33: 12650 | AA33: 8 | AB33: 1 | AC33: 2 | AD33: 2 | AE33: 8 | AF33: 20214.79 | AG33: 12650
A34: I_IOA. | B34: J_MAO. | C34: K40_R. | D34: C_02 | E34: 11770 | F34: 11770 | G34: 11770 | H34: 11770 | I34: 11770 | J34: 11770 | K34: 11770 | L34: 11770 | M34: 11770 | N34: 11770 | O34: 11770 | P34: 11770 | R34: 8 | S34: 1 | T34: 2 | U34: 2 | V34: 9 | W34: 20214.79 | X34: 12650 | AA34: 8 | AB34: 1 | AC34: 2 | AD34: 2 | AE34: 9 | AF34: 20214.79 | AG34: 12650
A35: I_IOA. | B35: J_PEC. | C35: K20_D. | D35: C_01 | E35: 7040 | F35: 7040 | G35: 7040 | H35: 7040 | I35: 7040 | J35: 7040 | K35: 7040 | L35: 7040 | M35: 7040 | N35: 7040 | O35: 7040 | P35: 7040 | R35: 8 | S35: 1 | T35: 2 | U35: 2 | V35: 10 | W35: 20214.79 | X35: 12650 | AA35: 8 | AB35: 1 | AC35: 2 | AD35: 2 | AE35: 10 | AF35: 20214.79 | AG35: 12650
A36: I_IOA. | B36: J_PEC. | C36: K40_D. | D36: C_01 | E36: 7700 | F36: 7700 | G36: 7700 | H36: 7700 | I36: 7700 | J36: 7700 | K36: 7700 | L36: 7700 | M36: 7700 | N36: 7700 | O36: 7700 | P36: 7700 | R36: 8 | S36: 1 | T36: 2 | U36: 2 | V36: 11 | W36: 20214.79 | X36: 12650 | AA36: 8 | AB36: 1 | AC36: 2 | AD36: 2 | AE36: 11 | AF36: 20214.79 | AG36: 12650
A37: I_IOA. | B37: J_PEC. | C37: K40_R. | D37: C_02 | E37: 9900 | F37: 9900 | G37: 9900 | H37: 9900 | I37: 9900 | J37: 9900 | K37: 9900 | L37: 9900 | M37: 9900 | N37: 9900 | O37: 9900 | P37: 9900 | R37: 8 | S37: 1 | T37: 2 | U37: 2 | V37: 12 | W37: 20214.79 | X37: 12650 | AA37: 8 | AB37: 1 | AC37: 2 | AD37: 2 | AE37: 12 | AF37: 20214.79 | AG37: 12650
A38: I_IOA. | B38: J_PNG. | C38: K20_D. | D38: C_01 | E38: 2200 | F38: 2200 | G38: 2200 | H38: 2200 | I38: 2200 | J38: 2200 | K38: 2200 | L38: 2200 | M38: 2200 | N38: 2200 | O38: 2200 | P38: 2200 | R38: 7 | S38: 1 | T38: 2 | U38: 2 | V38: 1 | W38: 0 | X38: 11770 | AA38: 7 | AB38: 1 | AC38: 2 | AD38: 2 | AE38: 1 | AF38: 0 | AG38: 11770
... A73: I_PEC. | B73: J_IGI. | C73: K20_D. | D73: C_01 | E73: 5830 | F73: 5830 | G73: 5830 | H73: 5830 | I73: 5830 | J73: 5830 | K73: 5830 | L73: 5830 | M73: 5830 | N73: 5830 | O73: 5830 | P73: 5830 | R73: 4 | S73: 1 | T73: 2 | U73: 2 | V73: 12 | W73: 0 | X73: 11330 | AA73: 4 | AB73: 1 | AC73: 2 | AD73: 2 | AE73: 12 | AF73: 0 | AG73: 11330
A74: I_PEC. | B74: J_IGI. | C74: K40_D. | D74: C_01 | E74: 6490 | F74: 6490 | G74: 6490 | H74: 6490 | I74: 6490 | J74: 6490 | K74: 6490 | L74: 6490 | M74: 6490 | N74: 6490 | O74: 6490 | P74: 6490 | R74: 3 | S74: 1 | T74: 2 | U74: 2 | V74: 1 | W74: 18365.02 | X74: 11170 | Y74: x | AA74: 3 | AB74: 1 | AC74: 2 | AD74: 2 | AE74: 1 | AF74: 18365.02 | AG74: 11170
A75: I_PEC. | B75: J_IGI. | C75: K40_R. | D75: C_02 | E75: 8690 | F75: 8690 | G75: 8690 | H75: 8690 | I75: 8690 | J75: 8690 | K75: 8690 | L75: 8690 | M75: 8690 | N75: 8690 | O75: 8690 | P75: 8690 | R75: 3 | S75: 1 | T75: 2 | U75: 2 | V75: 2 | W75: 18365.02 | X75: 11170 | AA75: 3 | AB75: 1 | AC75: 2 | AD75: 2 | AE75: 2 | AF75: 18365.02 | AG75: 11170
A76: I_PEC. | B76: J_IOA. | C76: K20_D. | D76: C_01 | E76: 3740 | F76: 3740 | G76: 3740 | H76: 3740 | I76: 3740 | J76: 3740 | K76: 3740 | L76: 3740 | M76: 3740 | N76: 3740 | O76: 3740 | P76: 3740 | R76: 3 | S76: 1 | T76: 2 | U76: 2 | V76: 3 | W76: 18365.02 | X76: 11170 | AA76: 3 | AB76: 1 | AC76: 2 | AD76: 2 | AE76: 3 | AF76: 18365.02 | AG76: 11170
A77: I_PEC. | B77: J_IOA. | C77: K40_D. | D77: C_01 | E77: 4400 | F77: 4400 | G77: 4400 | H77: 4400 | I77: 4400 | J77: 4400 | K77: 4400 | L77: 4400 | M77: 4400 | N77: 4400 | O77: 4400 | P77: 4400 | R77: 3 | S77: 1 | T77: 2 | U77: 2 | V77: 4 | W77: 18365.02 | X77: 11170 | AA77: 3 | AB77: 1 | AC77: 2 | AD77: 2 | AE77: 4 | AF77: 18365.02 | AG77: 11170
A78: I_PEC. | B78: J_IOA. | C78: K40_R. | D78: C_02 | E78: 3800 | F78: 3800 | G78: 3800 | H78: 3800 | I78: 3800 | J78: 3800 | K78: 3800 | L78: 3800 | M78: 3800 | N78: 3800 | O78: 3800 | P78: 3800 | R78: 3 | S78: 1 | T78: 2 | U78: 2 | V78: 5 | W78: 18365.02 | X78: 11170 | AA78: 3 | AB78: 1 | AC78: 2 | AD78: 2 | AE78: 5 | AF78: 18365.02 | AG78: 11170
A79: I_PEC. | B79: J_MAO. | C79: K20_D. | D79: C_01 | E79: 8210 | F79: 8210 | G79: 8210 | H79: 8210 | I79: 8210 | J79: 8210 | K79: 8210 | L79: 8210 | M79: 8210 | N79: 8210 | O79: 8210 | P79: 8210 | R79: 3 | S79: 1 | T79: 2 | U79: 2 | V79: 6 | W79: 18365.02 | X79: 11170 | AA79: 3 | AB79: 1 | AC79: 2 | AD79: 2 | AE79: 6 | AF79: 18365.02 | AG79: 11170
A80: I_PEC. | B80: J_MAO. | C80: K20_R. | D80: C_02 | E80: 5200 | F80: 5200 | G80: 5200 | H80: 5200 | I80: 5200 | J80: 5200 | K80: 5200 | L80: 5200 | M80: 5200 | N80: 5200 | O80: 5200 | P80: 5200 | R80: 3 | S80: 1 | T80: 2 | U80: 2 | V80: 7 | W80: 18365.02 | X80: 11170 | AA80: 3 | AB80: 1 | AC80: 2 | AD80: 2 | AE80: 7 | AF80: 18365.02 | AG80: 11170
A81: I_PEC. | B81: J_MAO. | C81: K40_D. | D81: C_01 | E81: 9602 | F81: 9602 | G81: 9602 | H81: 9602 | I81: 9602 | J81: 9602 | K81: 9602 | L81: 9602 | M81: 9602 | N81: 9602 | O81: 9602 | P81: 9602 | R81: 3 | S81: 1 | T81: 2 | U81: 2 | V81: 8 | W81: 18365.02 | X81: 11170 | AA81: 3 | AB81: 1 | AC81: 2 | AD81: 2 | AE81: 8 | AF81: 18365.02 | AG81: 11170
A82: I_PEC. | B82: J_MAO. | C82: K40_R. | D82: C_02 | E82: 10600 | F82: 10600 | G82: 10600 | H82: 10600 | I82: 10600 | J82: 10600 | K82: 10600 | L82: 10600 | M82: 10600 | N82: 10600 | O82: 10600 | P82: 10600 | R82: 3 | S82: 1 | T82: 2 | U82: 2 | V82: 9 | W82: 18365.02 | X82: 11170 | AA82: 3 | AB82: 1 | AC82: 2 | AD82: 2 | AE82: 9 | AF82: 18365.02 | AG82: 11170
A83: I_PEC. | B83: J_PNG. | C83: K20_D. | D83: C_01 | E83: 3740 | F83: 3740 | G83: 3740 | H83: 3740 | I83: 3740 | J83: 3740 | K83: 3740 | L83: 3740 | M83: 3740 | N83: 3740 | O83: 3740 | P83: 3740 | R83: 3 | S83: 1 | T83: 2 | U83: 2 | V83: 10 | W83: 18365.02 | X83: 11170 | AA83: 3 | AB83: 1 | AC83: 2 | AD83: 2 | AE83: 10 | AF83: 18365.02 | AG83: 11170
A84: I_PEC. | B84: J_PNG. | C84: K40_D. | D84: C_01 | E84: 4400 | F84: 4400 | G84: 4400 | H84: 4400 | I84: 4400 | J84: 4400 | K84: 4400 | L84: 4400 | M84: 4400 | N84: 4400 | O84: 4400 | P84: 4400 | R84: 3 | S84: 1 | T84: 2 | U84: 2 | V84: 11 | W84: 18365.02 | X84: 11170 | AA84: 3 | AB84: 1 | AC84: 2 | AD84: 2 | AE84: 11 | AF84: 18365.02 | AG84: 11170
A85: I_PEC. | B85: J_PNG. | C85: K40_R. | D85: C_02 | E85: 3800 | F85: 3800 | G85: 3800 | H85: 3800 | I85: 3800 | J85: 3800 | K85: 3800 | L85: 3800 | M85: 3800 | N85: 3800 | O85: 3800 | P85: 3800 | R85: 3 | S85: 1 | T85: 2 | U85: 2 | V85: 12 | W85: 18365.02 | X85: 11170 | AA85: 3 | AB85: 1 | AC85: 2 | AD85: 2 | AE85: 12 | AF85: 18365.02 | AG85: 11170
A86: I_PEC. | B86: J_SSA. | C86: K20_D. | D86: C_01 | E86: 2640 | F86: 2640 | G86: 2640 | H86: 2640 | I86: 2640 | J86: 2640 | K86: 2640 | L86: 2640 | M86: 2640 | N86: 2640 | O86: 2640 | P86: 2640 | R86: 8 | S86: 3 | T86: 2 | U86: 2 | V86: 1 | W86: 14071.18 | X86: 10780 | Y86: x | AA86: 8 | AB86: 3 | AC86: 2 | AD86: 2 | AE86: 1 | AF86: 14071.18 | AG86: 10780
A87: I_PEC. | B87: J_SSA. | C87: K40_D. | D87: C_01 | E87: 3300 | F87: 3300 | G87: 3300 | H87: 3300 | I87: 3300 | J87: 3300 | K87: 3300 | L87: 3300 | M87: 3300 | N87: 3300 | O87: 3300 | P87: 3300 | R87: 8 | S87: 3 | T87: 2 | U87: 2 | V87: 2 | W87: 14071.18 | X87: 10780 | AA87: 8 | AB87: 3 | AC87: 2 | AD87: 2 | AE87: 2 | AF87: 14071.18 | AG87: 10780
A88: I_PEC. | B88: J_SSZ. | C88: K20_D. | D88: C_01 | E88: 4400 | F88: 4400 | G88: 4400 | H88: 4400 | I88: 4400 | J88: 4400 | K88: 4400 | L88: 4400 | M88: 4400 | N88: 4400 | O88: 4400 | P88: 4400 | R88: 8 | S88: 3 | T88: 2 | U88: 2 | V88: 3 | W88: 14071.18 | X88: 10780 | AA88: 8 | AB88: 3 | AC88: 2 | AD88: 2 | AE88: 3 | AF88: 14071.18 | AG88: 10780
A89: I_PEC. | B89: J_SSZ. | C89: K20_R. | D89: C_02 | E89: 6600 | F89: 6600 | G89: 6600 | H89: 6600 | I89: 6600 | J89: 6600 | K89: 6600 | L89: 6600 | M89: 6600 | N89: 6600 | O89: 6600 | P89: 6600 | R89: 8 | S89: 3 | T89: 2 | U89: 2 | V89: 4 | W89: 14071.18 | X89: 10780 | AA89: 8 | AB89: 3 | AC89: 2 | AD89: 2 | AE89: 4 | AF89: 14071.18 | AG89: 10780
A90: I_PEC. | B90: J_SSZ. | C90: K40_D. | D90: C_01 | E90: 5060 | F90: 5060 | G90: 5060 | H90: 5060 | I90: 5060 | J90: 5060 | K90: 5060 | L90: 5060 | M90: 5060 | N90: 5060 | O90: 5060 | P90: 5060 | R90: 8 | S90: 3 | T90: 2 | U90: 2 | V90: 5 | W90: 14071.18 | X90: 10780 | AA90: 8 | AB90: 3 | AC90: 2 | AD90: 2 | AE90: 5 | AF90: 14071.18 | AG90: 10780
A91: I_PEC. | B91: J_SSZ. | C91: K40_R. | D91: C_02 | E91: 7260 | F91: 7260 | G91: 7260 | H91: 7260 | I91: 7260 | J91: 7260 | K91: 7260 | L91: 7260 | M91: 7260 | N91: 7260 | O91: 7260 | P91: 7260 | R91: 8 | S91: 3 | T91: 2 | U91: 2 | V91: 6 | W91: 14071.18 | X91: 10780 | AA91: 8 | AB91: 3 | AC91: 2 | AD91: 2 | AE91: 6 | AF91: 14071.18 | AG91: 10780
A92: I_PEC. | B92: J_SUA. | C92: K20_D. | D92: C_01 | E92: 2640 | F92: 2640 | G92: 2640 | H92: 2640 | I92: 2640 | J92: 2640 | K92: 2640 | L92: 2640 | M92: 2640 | N92: 2640 | O92: 2640 | P92: 2640 | R92: 8 | S92: 3 | T92: 2 | U92: 2 | V92: 7 | W92: 14071.18 | X92: 10780 | AA92: 8 | AB92: 3 | AC92: 2 | AD92: 2 | AE92: 7 | AF92: 14071.18 | AG92: 10780
A93: I_PEC. | B93: J_SUA. | C93: K40_D. | D93: C_01 | E93: 3300 | F93: 3300 | G93: 3300 | H93: 3300 | I93: 3300 | J93: 3300 | K93: 3300 | L93: 3300 | M93: 3300 | N93: 3300 | O93: 3300 | P93: 3300 | R93: 8 | S93: 3 | T93: 2 | U93: 2 | V93: 8 | W93: 14071.18 | X93: 10780 | AA93: 8 | AB93: 3 | AC93: 2 | AD93: 2 | AE93: 8 | AF93: 14071.18 | AG93: 10780
A94: I_PNG. | B94: J_IGI. | C94: K20_D. | D94: C_01 | E94: 2310 | F94: 2310 | G94: 2310 | H94: 2310 | I94: 2310 | J94: 2310 | K94: 2310 | L94: 2310 | M94: 2310 | N94: 2310 | O94: 2310 | P94: 2310 | R94: 8 | S94: 3 | T94: 2 | U94: 2 | V94: 9 | W94: 14071.18 | X94: 10780 | AA94: 8 | AB94: 3 | AC94: 2 | AD94: 2 | AE94: 9 | AF94: 14071.18 | AG94: 10780
A95: I_PNG. | B95: J_IGI. | C95: K20_R. | D95: C_02 | E95: 3500 | F95: 3500 | G95: 3500 | H95: 3500 | I95: 3500 | J95: 3500 | K95: 3500 | L95: 3500 | M95: 3500 | N95: 3500 | O95: 3500 | P95: 3500 | R95: 8 | S95: 3 | T95: 2 | U95: 2 | V95: 10 | W95: 14071.18 | X95: 10780 | AA95: 8 | AB95: 3 | AC95: 2 | AD95: 2 | AE95: 10 | AF95: 14071.18 | AG95: 10780
A96: I_PNG. | B96: J_IGI. | C96: K40_D. | D96: C_01 | E96: 2970 | F96: 2970 | G96: 2970 | H96: 2970 | I96: 2970 | J96: 2970 | K96: 2970 | L96: 2970 | M96: 2970 | N96: 2970 | O96: 2970 | P96: 2970 | R96: 8 | S96: 3 | T96: 2 | U96: 2 | V96: 11 | W96: 14071.18 | X96: 10780 | AA96: 8 | AB96: 3 | AC96: 2 | AD96: 2 | AE96: 11 | AF96: 14071.18 | AG96: 10780
A97: I_PNG. | B97: J_IGI. | C97: K40_R. | D97: C_02 | E97: 5170 | F97: 5170 | G97: 5170 | H97: 5170 | I97: 5170 | J97: 5170 | K97: 5170 | L97: 5170 | M97: 5170 | N97: 5170 | O97: 5170 | P97: 5170 | R97: 8 | S97: 3 | T97: 2 | U97: 2 | V97: 12 | W97: 14071.18 | X97: 10780 | AA97: 8 | AB97: 3 | AC97: 2 | AD97: 2 | AE97: 12 | AF97: 14071.18 | AG97: 10780
A98: I_PNG. | B98: J_MAO. | C98: K20_D. | D98: C_01 | E98: 8910 | F98: 8910 | G98: 8910 | H98: 8910 | I98: 8910 | J98: 8910 | K98: 8910 | L98: 8910 | M98: 8910 | N98: 8910 | O98: 8910 | P98: 8910 | R98: 2 | S98: 1 | T98: 2 | U98: 2 | V98: 1 | W98: 16894.04 | X98: 10600 | Y98: x | AA98: 2 | AB98: 1 | AC98: 2 | AD98: 2 | AE98: 1 | AF98: 16894.04 | AG98: 10600
A99: I_PNG. | B99: J_MAO. | C99: K40_D. | D99: C_01 | E99: 10450 | F99: 10450 | G99: 10450 | H99: 10450 | I99: 10450 | J99: 10450 | K99: 10450 | L99: 10450 | M99: 10450 | N99: 10450 | O99: 10450 | P99: 10450 | R99: 2 | S99: 1 | T99: 2 | U99: 2 | V99: 2 | W99: 16894.04 | X99: 10600 | AA99: 2 | AB99: 1 | AC99: 2 | AD99: 2 | AE99: 2 | AF99: 16894.04 | AG99: 10600
A100: I_PNG. | B100: J_MAO. | C100: K40_R. | D100: C_02 | E100: 12650 | F100: 12650 | G100: 12650 | H100: 12650 | I100: 12650 | J100: 12650 | K100: 12650 | L100: 12650 | M100: 12650 | N100: 12650 | O100: 12650 | P100: 12650 | R100: 2 | S100: 1 | T100: 2 | U100: 2 | V100: 3 | W100: 16894.04 | X100: 10600 | AA100: 2 | AB100: 1 | AC100: 2 | AD100: 2 | AE100: 3 | AF100: 16894.04 | AG100: 10600
A101: I_PNG. | B101: J_PEC. | C101: K20_D. | D101: C_01 | E101: 7150 | F101: 7150 | G101: 7150 | H101: 7150 | I101: 7150 | J101: 7150 | K101: 7150 | L101: 7150 | M101: 7150 | N101: 7150 | O101: 7150 | P101: 7150 | R101: 2 | S101: 1 | T101: 2 | U101: 2 | V101: 4 | W101: 16894.04 | X101: 10600 | AA101: 2 | AB101: 1 | AC101: 2 | AD101: 2 | AE101: 4 | AF101: 16894.04 | AG101: 10600
A102: I_PNG. | B102: J_PEC. | C102: K40_D. | D102: C_01 | E102: 8030 | F102: 8030 | G102: 8030 | H102: 8030 | I102: 8030 | J102: 8030 | K102: 8030 | L102: 8030 | M102: 8030 | N102: 8030 | O102: 8030 | P102: 8030 | R102: 2 | S102: 1 | T102: 2 | U102: 2 | V102: 5 | W102: 16894.04 | X102: 10600 | AA102: 2 | AB102: 1 | AC102: 2 | AD102: 2 | AE102: 5 | AF102: 16894.04 | AG102: 10600
A103: I_PNG. | B103: J_PEC. | C103: K40_R. | D103: C_02 | E103: 10230 | F103: 10230 | G103: 10230 | H103: 10230 | I103: 10230 | J103: 10230 | K103: 10230 | L103: 10230 | M103: 10230 | N103: 10230 | O103: 10230 | P103: 10230 | R103: 2 | S103: 1 | T103: 2 | U103: 2 | V103: 6 | W103: 16894.04 | X103: 10600 | AA103: 2 | AB103: 1 | AC103: 2 | AD103: 2 | AE103: 6 | AF103: 16894.04 | AG103: 10600
A104: I_PNG. | B104: J_SSA. | C104: K20_D. | D104: C_01 | E104: 7260 | F104: 7260 | G104: 7260 | H104: 7260 | I104: 7260 | J104: 7260 | K104: 7260 | L104: 7260 | M104: 7260 | N104: 7260 | O104: 7260 | P104: 7260 | R104: 2 | S104: 1 | T104: 2 | U104: 2 | V104: 7 | W104: 16894.04 | X104: 10600 | AA104: 2 | AB104: 1 | AC104: 2 | AD104: 2 | AE104: 7 | AF104: 16894.04 | AG104: 10600
A105: I_PNG. | B105: J_SSA. | C105: K40_D. | D105: C_01 | E105: 7920 | F105: 7920 | G105: 7920 | H105: 7920 | I105: 7920 | J105: 7920 | K105: 7920 | L105: 7920 | M105: 7920 | N105: 7920 | O105: 7920 | P105: 7920 | R105: 2 | S105: 1 | T105: 2 | U105: 2 | V105: 8 | W105: 16894.04 | X105: 10600 | AA105: 2 | AB105: 1 | AC105: 2 | AD105: 2 | AE105: 8 | AF105: 16894.04 | AG105: 10600
A106: I_PNG. | B106: J_SSA. | C106: K40_R. | D106: C_02 | E106: 10120 | F106: 10120 | G106: 10120 | H106: 10120 | I106: 10120 | J106: 10120 | K106: 10120 | L106: 10120 | M106: 10120 | N106: 10120 | O106: 10120 | P106: 10120 | R106: 2 | S106: 1 | T106: 2 | U106: 2 | V106: 9 | W106: 16894.04 | X106: 10600 | AA106: 2 | AB106: 1 | AC106: 2 | AD106: 2 | AE106: 9 | AF106: 16894.04 | AG106: 10600
A107: I_PNG. | B107: J_SSZ. | C107: K20_D. | D107: C_01 | E107: 2000 | F107: 2000 | G107: 2000 | H107: 2000 | I107: 2000 | J107: 2000 | K107: 2000 | L107: 2000 | M107: 2000 | N107: 2000 | O107: 2000 | P107: 2000 | R107: 2 | S107: 1 | T107: 2 | U107: 2 | V107: 10 | W107: 16894.04 | X107: 10600 | AA107: 2 | AB107: 1 | AC107: 2 | AD107: 2 | AE107: 10 | AF107: 16894.04 | AG107: 10600
A108: I_PNG. | B108: J_SSZ. | C108: K20_R. | D108: C_02 | E108: 4400 | F108: 4400 | G108: 4400 | H108: 4400 | I108: 4400 | J108: 4400 | K108: 4400 | L108: 4400 | M108: 4400 | N108: 4400 | O108: 4400 | P108: 4400 | R108: 2 | S108: 1 | T108: 2 | U108: 2 | V108: 11 | W108: 16894.04 | X108: 10600 | AA108: 2 | AB108: 1 | AC108: 2 | AD108: 2 | AE108: 11 | AF108: 16894.04 | AG108: 10600
A109: I_PNG. | B109: J_SSZ. | C109: K40_D. | D109: C_01 | E109: 2750 | F109: 2750 | G109: 2750 | H109: 2750 | I109: 2750 | J109: 2750 | K109: 2750 | L109: 2750 | M109: 2750 | N109: 2750 | O109: 2750 | P109: 2750 | R109: 2 | S109: 1 | T109: 2 | U109: 2 | V109: 12 | W109: 16894.04 | X109: 10600 | AA109: 2 | AB109: 1 | AC109: 2 | AD109: 2 | AE109: 12 | AF109: 16894.04 | AG109: 10600
A110: I_PNG. | B110: J_SSZ. | C110: K40_R. | D110: C_02 | E110: 4950 | F110: 4950 | G110: 4950 | H110: 4950 | I110: 4950 | J110: 4950 | K110: 4950 | L110: 4950 | M110: 4950 | N110: 4950 | O110: 4950 | P110: 4950 | R110: 8 | S110: 1 | T110: 1 | U110: 1 | V110: 1 | W110: 13614.84 | X110: 10450 | Y110: x | AA110: 8 | AB110: 1 | AC110: 1 | AD110: 1 | AE110: 1 | AF110: 13614.84 | AG110: 10450
A111: I_PNG. | B111: J_SUA. | C111: K20_D. | D111: C_01 | E111: 7920 | F111: 7920 | G111: 7920 | H111: 7920 | I111: 7920 | J111: 7920 | K111: 7920 | L111: 7920 | M111: 7920 | N111: 7920 | O111: 7920 | P111: 7920 | R111: 8 | S111: 1 | T111: 1 | U111: 1 | V111: 2 | W111: 13614.84 | X111: 10450 | AA111: 8 | AB111: 1 | AC111: 1 | AD111: 1 | AE111: 2 | AF111: 13614.84 | AG111: 10450
A112: I_PNG. | B112: J_SUA. | C112: K20_R. | D112: C_02 | E112: 5200 | F112: 5200 | G112: 5200 | H112: 5200 | I112: 5200 | J112: 5200 | K112: 5200 | L112: 5200 | M112: 5200 | N112: 5200 | O112: 5200 | P112: 5200 | R112: 8 | S112: 1 | T112: 1 | U112: 1 | V112: 3 | W112: 13614.84 | X112: 10450 | AA112: 8 | AB112: 1 | AC112: 1 | AD112: 1 | AE112: 3 | AF112: 13614.84 | AG112: 10450
A113: I_PNG. | B113: J_SUA. | C113: K40_D. | D113: C_01 | E113: 8580 | F113: 8580 | G113: 8580 | H113: 8580 | I113: 8580 | J113: 8580 | K113: 8580 | L113: 8580 | M113: 8580 | N113: 8580 | O113: 8580 | P113: 8580 | R113: 8 | S113: 1 | T113: 1 | U113: 1 | V113: 4 | W113: 13614.84 | X113: 10450 | AA113: 8 | AB113: 1 | AC113: 1 | AD113: 1 | AE113: 4 | AF113: 13614.84 | AG113: 10450
A114: I_PNG. | B114: J_SUA. | C114: K40_R. | D114: C_02 | E114: 10780 | F114: 10780 | G114: 10780 | H114: 10780 | I114: 10780 | J114: 10780 | K114: 10780 | L114: 10780 | M114: 10780 | N114: 10780 | O114: 10780 | P114: 10780 | R114: 8 | S114: 1 | T114: 1 | U114: 1 | V114: 5 | W114: 13614.84 | X114: 10450 | AA114: 8 | AB114: 1 | AC114: 1 | AD114: 1 | AE114: 5 | AF114: 13614.84 | AG114: 10450
A115: I_SSA. | B115: J_IGI. | C115: K20_D. | D115: C_01 | E115: 2750 | F115: 2750 | G115: 2750 | H115: 2750 | I115: 2750 | J115: 2750 | K115: 2750 | L115: 2750 | M115: 2750 | N115: 2750 | O115: 2750 | P115: 2750 | R115: 8 | S115: 1 | T115: 1 | U115: 1 | V115: 6 | W115: 13614.84 | X115: 10450 | AA115: 8 | AB115: 1 | AC115: 1 | AD115: 1 | AE115: 6 | AF115: 13614.84 | AG115: 10450
A116: I_SSA. | B116: J_IGI. | C116: K40_D. | D116: C_01 | E116: 3410 | F116: 3410 | G116: 3410 | H116: 3410 | I116: 3410 | J116: 3410 | K116: 3410 | L116: 3410 | M116: 3410 | N116: 3410 | O116: 3410 | P116: 3410 | R116: 8 | S116: 1 | T116: 1 | U116: 1 | V116: 7 | W116: 13614.84 | X116: 10450 | AA116: 8 | AB116: 1 | AC116: 1 | AD116: 1 | AE116: 7 | AF116: 13614.84 | AG116: 10450
A117: I_SSA. | B117: J_IGI. | C117: K40_R. | D117: C_02 | E117: 5610 | F117: 5610 | G117: 5610 | H117: 5610 | I117: 5610 | J117: 5610 | K117: 5610 | L117: 5610 | M117: 5610 | N117: 5610 | O117: 5610 | P117: 5610 | R117: 8 | S117: 1 | T117: 1 | U117: 1 | V117: 8 | W117: 13614.84 | X117: 10450 | AA117: 8 | AB117: 1 | AC117: 1 | AD117: 1 | AE117: 8 | AF117: 13614.84 | AG117: 10450
A118: I_SSA. | B118: J_IOA. | C118: K20_D. | D118: C_01 | E118: 4950 | F118: 4950 | G118: 4950 | H118: 4950 | I118: 4950 | J118: 4950 | K118: 4950 | L118: 4950 | M118: 4950 | N118: 4950 | O118: 4950 | P118: 4950 | R118: 8 | S118: 1 | T118: 1 | U118: 1 | V118: 9 | W118: 13614.84 | X118: 10450 | AA118: 8 | AB118: 1 | AC118: 1 | AD118: 1 | AE118: 9 | AF118: 13614.84 | AG118: 10450
A119: I_SSA. | B119: J_IOA. | C119: K40_D. | D119: C_01 | E119: 5610 | F119: 5610 | G119: 5610 | H119: 5610 | I119: 5610 | J119: 5610 | K119: 5610 | L119: 5610 | M119: 5610 | N119: 5610 | O119: 5610 | P119: 5610 | R119: 8 | S119: 1 | T119: 1 | U119: 1 | V119: 10 | W119: 13614.84 | X119: 10450 | AA119: 8 | AB119: 1 | AC119: 1 | AD119: 1 | AE119: 10 | AF119: 13614.84 | AG119: 10450
A120: I_SSA. | B120: J_IOA. | C120: K40_R. | D120: C_02 | E120: 3500 | F120: 3500 | G120: 3500 | H120: 3500 | I120: 3500 | J120: 3500 | K120: 3500 | L120: 3500 | M120: 3500 | N120: 3500 | O120: 3500 | P120: 3500 | R120: 8 | S120: 1 | T120: 1 | U120: 1 | V120: 11 | W120: 13614.84 | X120: 10450 | AA120: 8 | AB120: 1 | AC120: 1 | AD120: 1 | AE120: 11 | AF120: 13614.84 | AG120: 10450
A121: I_SSA. | B121: J_MAO. | C121: K20_D. | D121: C_01 | E121: 8470 | F121: 8470 | G121: 8470 | H121: 8470 | I121: 8470 | J121: 8470 | K121: 8470 | L121: 8470 | M121: 8470 | N121: 8470 | O121: 8470 | P121: 8470 | R121: 8 | S121: 1 | T121: 1 | U121: 1 | V121: 12 | W121: 13614.84 | X121: 10450 | AA121: 8 | AB121: 1 | AC121: 1 | AD121: 1 | AE121: 12 | AF121: 13614.84 | AG121: 10450
A122: I_SSA. | B122: J_MAO. | C122: K40_D. | D122: C_01 | E122: 9130 | F122: 9130 | G122: 9130 | H122: 9130 | I122: 9130 | J122: 9130 | K122: 9130 | L122: 9130 | M122: 9130 | N122: 9130 | O122: 9130 | P122: 9130 | R122: 6 | S122: 1 | T122: 3 | U122: 1 | V122: 1 | W122: 12145.08 | X122: 10360 | Y122: x | AA122: 6 | AB122: 1 | AC122: 3 | AD122: 1 | AE122: 1 | AF122: 12145.08 | AG122: 10360
A123: I_SSA. | B123: J_MAO. | C123: K40_R. | D123: C_02 | E123: 11330 | F123: 11330 | G123: 11330 | H123: 11330 | I123: 11330 | J123: 11330 | K123: 11330 | L123: 11330 | M123: 11330 | N123: 11330 | O123: 11330 | P123: 11330 | R123: 6 | S123: 1 | T123: 3 | U123: 1 | V123: 2 | W123: 12145.08 | X123: 10360 | AA123: 6 | AB123: 1 | AC123: 3 | AD123: 1 | AE123: 2 | AF123: 12145.08 | AG123: 10360
A124: I_SSA. | B124: J_PEC. | C124: K20_D. | D124: C_01 | E124: 3850 | F124: 3850 | G124: 3850 | H124: 3850 | I124: 3850 | J124: 3850 | K124: 3850 | L124: 3850 | M124: 3850 | N124: 3850 | O124: 3850 | P124: 3850 | R124: 6 | S124: 1 | T124: 3 | U124: 1 | V124: 3 | W124: 12145.08 | X124: 10360 | AA124: 6 | AB124: 1 | AC124: 3 | AD124: 1 | AE124: 3 | AF124: 12145.08 | AG124: 10360
A125: I_SSA. | B125: J_PEC. | C125: K40_D. | D125: C_01 | E125: 4510 | F125: 4510 | G125: 4510 | H125: 4510 | I125: 4510 | J125: 4510 | K125: 4510 | L125: 4510 | M125: 4510 | N125: 4510 | O125: 4510 | P125: 4510 | R125: 6 | S125: 1 | T125: 3 | U125: 1 | V125: 4 | W125: 12145.08 | X125: 10360 | AA125: 6 | AB125: 1 | AC125: 3 | AD125: 1 | AE125: 4 | AF125: 12145.08 | AG125: 10360
A126: I_SSA. | B126: J_PEC. | C126: K40_R. | D126: C_02 | E126: 5000 | F126: 5000 | G126: 5000 | H126: 5000 | I126: 5000 | J126: 5000 | K126: 5000 | L126: 5000 | M126: 5000 | N126: 5000 | O126: 5000 | P126: 5000 | R126: 6 | S126: 1 | T126: 3 | U126: 1 | V126: 5 | W126: 12145.08 | X126: 10360 | AA126: 6 | AB126: 1 | AC126: 3 | AD126: 1 | AE126: 5 | AF126: 12145.08 | AG126: 10360
A127: I_SSA. | B127: J_PNG. | C127: K20_D. | D127: C_01 | E127: 2400 | F127: 2400 | G127: 2400 | H127: 2400 | I127: 2400 | J127: 2400 | K127: 2400 | L127: 2400 | M127: 2400 | N127: 2400 | O127: 2400 | P127: 2400 | R127: 6 | S127: 1 | T127: 3 | U127: 1 | V127: 6 | W127: 12145.08 | X127: 10360 | AA127: 6 | AB127: 1 | AC127: 3 | AD127: 1 | AE127: 6 | AF127: 12145.08 | AG127: 10360
A128: I_SSA. | B128: J_PNG. | C128: K40_D. | D128: C_01 | E128: 5280 | F128: 5280 | G128: 5280 | H128: 5280 | I128: 5280 | J128: 5280 | K128: 5280 | L128: 5280 | M128: 5280 | N128: 5280 | O128: 5280 | P128: 5280 | R128: 6 | S128: 1 | T128: 3 | U128: 1 | V128: 7 | W128: 12145.08 | X128: 10360 | AA128: 6 | AB128: 1 | AC128: 3 | AD128: 1 | AE128: 7 | AF128: 12145.08 | AG128: 10360
A129: I_SSA. | B129: J_PNG. | C129: K40_R. | D129: C_02 | E129: 3500 | F129: 3500 | G129: 3500 | H129: 3500 | I129: 3500 | J129: 3500 | K129: 3500 | L129: 3500 | M129: 3500 | N129: 3500 | O129: 3500 | P129: 3500 | R129: 6 | S129: 1 | T129: 3 | U129: 1 | V129: 8 | W129: 12145.08 | X129: 10360 | AA129: 6 | AB129: 1 | AC129: 3 | AD129: 1 | AE129: 8 | AF129: 12145.08 | AG129: 10360
A130: I_SSA. | B130: J_SSZ. | C130: K20_D. | D130: C_01 | E130: 3960 | F130: 3960 | G130: 3960 | H130: 3960 | I130: 3960 | J130: 3960 | K130: 3960 | L130: 3960 | M130: 3960 | N130: 3960 | O130: 3960 | P130: 3960 | R130: 6 | S130: 1 | T130: 3 | U130: 1 | V130: 9 | W130: 12145.08 | X130: 10360 | AA130: 6 | AB130: 1 | AC130: 3 | AD130: 1 | AE130: 9 | AF130: 12145.08 | AG130: 10360
A131: I_SSA. | B131: J_SSZ. | C131: K20_R. | D131: C_02 | E131: 6160 | F131: 6160 | G131: 6160 | H131: 6160 | I131: 6160 | J131: 6160 | K131: 6160 | L131: 6160 | M131: 6160 | N131: 6160 | O131: 6160 | P131: 6160 | R131: 6 | S131: 1 | T131: 3 | U131: 1 | V131: 10 | W131: 12145.08 | X131: 10360 | AA131: 6 | AB131: 1 | AC131: 3 | AD131: 1 | AE131: 10 | AF131: 12145.08 | AG131: 10360
A132: I_SSA. | B132: J_SSZ. | C132: K40_D. | D132: C_01 | E132: 4620 | F132: 4620 | G132: 4620 | H132: 4620 | I132: 4620 | J132: 4620 | K132: 4620 | L132: 4620 | M132: 4620 | N132: 4620 | O132: 4620 | P132: 4620 | R132: 6 | S132: 1 | T132: 3 | U132: 1 | V132: 11 | W132: 12145.08 | X132: 10360 | AA132: 6 | AB132: 1 | AC132: 3 | AD132: 1 | AE132: 11 | AF132: 12145.08 | AG132: 10360
A133: I_SSA. | B133: J_SSZ. | C133: K40_R. | D133: C_02 | E133: 6820 | F133: 6820 | G133: 6820 | H133: 6820 | I133: 6820 | J133: 6820 | K133: 6820 | L133: 6820 | M133: 6820 | N133: 6820 | O133: 6820 | P133: 6820 | R133: 6 | S133: 1 | T133: 3 | U133: 1 | V133: 12 | W133: 12145.08 | X133: 10360 | AA133: 6 | AB133: 1 | AC133: 3 | AD133: 1 | AE133: 12 | AF133: 12145.08 | AG133: 10360
A134: I_SSA. | B134: J_SUA. | C134: K20_D. | D134: C_01 | E134: 3300 | F134: 3300 | G134: 3300 | H134: 3300 | I134: 3300 | J134: 3300 | K134: 3300 | L134: 3300 | M134: 3300 | N134: 3300 | O134: 3300 | P134: 3300 | R134: 8 | S134: 2 | T134: 2 | U134: 2 | V134: 1 | W134: 12625.19 | X134: 10230 | Y134: x | AA134: 8 | AB134: 2 | AC134: 2 | AD134: 2 | AE134: 1 | AF134: 12625.19 | AG134: 10230
...

Sheet PAR E0
A1: Coluna1 | B1: K20_D | C1: K20_R | D1: K40_D | E1: K40_R | G1: I | H1: J | I1: E0
A2: I_MAO | B2: 0 | C2: 0 | D2: 0 | E2: 0 | G2: 1 | H2: 3 | I2: 0
A3: I_PEC | B3: 0 | C3: 0 | D3: 0 | E3: 0 | G3: 1 | H3: 4 | I3: 0
A4: I_SUA | B4: 0 | C4: 0 | D4: 0 | E4: 0 | G4: 1 | H4: 1 | I4: 0
A5: I_SSA | B5: 0 | C5: 0 | D5: 0 | E5: 0 | G5: 1 | H5: 2 | I5: 0
A6: I_IGI | B6: 0 | C6: 0 | D6: 0 | E6: 0 | G6: 2 | H6: 3 | I6: 0
A7: I_SSZ | B7: 0 | C7: 0 | D7: 0 | E7: 0 | G7: 2 | H7: 4 | I7: 0
A8: I_PNG | B8: 0 | C8: 0 | D8: 0 | E8: 0 | G8: 2 | H8: 1 | I8: 0
A9: I_IOA | B9: 0 | C9: 0 | D9: 0 | E9: 0 | G9: 2 | H9: 2 | I9: 0
G10: 3 | H10: 3 | I10: 0
G11: 3 | H11: 4 | I11: 0
G12: 3 | H12: 1 | I12: 0
G13: 3 | H13: 2 | I13: 0
G14: 4 | H14: 3 | I14: 0
G15: 4 | H15: 4 | I15: 0
G16: 4 | H16: 1 | I16: 0
G17: 4 | H17: 2 | I17: 0
G18: 5 | H18: 3 | I18: 0
G19: 5 | H19: 4 | I19: 0
G20: 5 | H20: 1 | I20: 0
G21: 5 | H21: 2 | I21: 0
... G33: 7 | H33: 2 | I33: 0

Sheet PAR WF
A1: Coluna1 | B1: K20_D | C1: K20_R | D1: K40_D | E1: K40_R | G1: C | H1: K | I1: WF
A2: C_01 | B2: 27 | C2: 0 | D2: 26 | E2: 0 | G2: 1 | H2: 3 | I2: 27
A3: C_02 | B3: 0 | C3: 9 | D3: 0 | E3: 29 | G3: 1 | H3: 4 | I3: 0
G4: 1 | H4: 1 | I4: 26
G5: 1 | H5: 2 | I5: 0
G6: 2 | H6: 3 | I6: 0
G7: 2 | H7: 4 | I7: 9
G8: 2 | H8: 1 | I8: 0
G9: 2 | H9: 2 | I9: 29

Sheet PAR WE
A1: WE('K20_D')= | B1: 2 | C1: ; | D1: K | E1: WE
A2: WE('K20_R')= | B2: 2 | C2: ; | D2: 3 | E2: 2
A3: WE('K40_D')= | B3: 4 | C3: ; | D3: 4 | E3: 2
A4: WE('K40_R')= | B4: 4 | C4: ; | D4: 1 | E4: 4
D5: 2 | E5: 4
A6: =LEFT(RIGHT(A1,8),5) -> K20_D
A7: =LEFT(RIGHT(A2,8),5) -> K20_R
A8: =LEFT(RIGHT(A3,8),5) -> K40_D
A9: =LEFT(RIGHT(A4,8),5) -> K40_R

Sheet PAR PX
A1: Coluna1 | B1: Coluna2 | C1: T_01 | D1: T_02 | E1: T_03 | F1: T_04 | G1: T_05 | H1: T_06 | I1: T_07 | J1: T_08 | K1: T_09 | L1: T_10 | M1: T_11 | N1: T_12 | P1: I | Q1: C | R1: T | S1: PX
A2: I_MAO. | B2: C_01 | C2: 1 | D2: 1 | E2: 1 | F2: 1 | G2: 1 | H2: 1 | I2: 1 | J2: 1 | K2: 1 | L2: 1 | M2: 1 | N2: 1 | P2: 1 | Q2: 1 | R2: 1 | S2: 1
A3: I_MAO. | B3: C_02 | C3: 1 | D3: 1 | E3: 1 | F3: 1 | G3: 1 | H3: 1 | I3: 1 | J3: 1 | K3: 1 | L3: 1 | M3: 1 | N3: 1 | P3: 1 | Q3: 1 | R3: 2 | S3: 1
A4: I_PEC. | B4: C_01 | C4: 1 | D4: 1 | E4: 1 | F4: 1 | G4: 1 | H4: 1 | I4: 1 | J4: 1 | K4: 1 | L4: 1 | M4: 1 | N4: 1 | P4: 1 | Q4: 1 | R4: 3 | S4: 1
A5: I_PEC. | B5: C_02 | C5: 1 | D5: 1 | E5: 1 | F5: 1 | G5: 1 | H5: 1 | I5: 1 | J5: 1 | K5: 1 | L5: 1 | M5: 1 | N5: 1 | P5: 1 | Q5: 1 | R5: 4 | S5: 1
A6: I_SUA. | B6: C_01 | C6: 1 | D6: 1 | E6: 1 | F6: 1 | G6: 1 | H6: 1 | I6: 1 | J6: 1 | K6: 1 | L6: 1 | M6: 1 | N6: 1 | P6: 1 | Q6: 1 | R6: 5 | S6: 1
A7: I_SUA. | B7: C_02 | C7: 1 | D7: 1 | E7: 1 | F7: 1 | G7: 1 | H7: 1 | I7: 1 | J7: 1 | K7: 1 | L7: 1 | M7: 1 | N7: 1 | P7: 1 | Q7: 1 | R7: 6 | S7: 1
A8: I_SSA. | B8: C_01 | C8: 1 | D8: 1 | E8: 1 | F8: 1 | G8: 1 | H8: 1 | I8: 1 | J8: 1 | K8: 1 | L8: 1 | M8: 1 | N8: 1 | P8: 1 | Q8: 1 | R8: 7 | S8: 1
A9: I_SSA. | B9: C_02 | C9: 1 | D9: 1 | E9: 1 | F9: 1 | G9: 1 | H9: 1 | I9: 1 | J9: 1 | K9: 1 | L9: 1 | M9: 1 | N9: 1 | P9: 1 | Q9: 1 | R9: 8 | S9: 1
A10: I_IGI. | B10: C_01 | C10: 1 | D10: 1 | E10: 1 | F10: 1 | G10: 1 | H10: 1 | I10: 1 | J10: 1 | K10: 1 | L10: 1 | M10: 1 | N10: 1 | P10: 1 | Q10: 1 | R10: 9 | S10: 1
A11: I_IGI. | B11: C_02 | C11: 1 | D11: 1 | E11: 1 | F11: 1 | G11: 1 | H11: 1 | I11: 1 | J11: 1 | K11: 1 | L11: 1 | M11: 1 | N11: 1 | P11: 1 | Q11: 1 | R11: 10 | S11: 1
A12: I_SSZ. | B12: C_01 | C12: 1 | D12: 1 | E12: 1 | F12: 1 | G12: 1 | H12: 1 | I12: 1 | J12: 1 | K12: 1 | L12: 1 | M12: 1 | N12: 1 | P12: 1 | Q12: 1 | R12: 11 | S12: 1
A13: I_SSZ. | B13: C_02 | C13: 1 | D13: 1 | E13: 1 | F13: 1 | G13: 1 | H13: 1 | I13: 1 | J13: 1 | K13: 1 | L13: 1 | M13: 1 | N13: 1 | P13: 1 | Q13: 1 | R13: 12 | S13: 1
... A17: I_IOA. | B17: C_02 | C17: 1 | D17: 1 | E17: 1 | F17: 1 | G17: 1 | H17: 1 | I17: 1 | J17: 1 | K17: 1 | L17: 1 | M17: 1 | N17: 1 | P17: 1 | Q17: 2 | R17: 4 | S17: 1
P18: 1 | Q18: 2 | R18: 5 | S18: 1
P19: 1 | Q19: 2 | R19: 6 | S19: 1
P20: 1 | Q20: 2 | R20: 7 | S20: 1
P21: 1 | Q21: 2 | R21: 8 | S21: 1
P22: 1 | Q22: 2 | R22: 9 | S22: 1
P23: 1 | Q23: 2 | R23: 10 | S23: 1
P24: 1 | Q24: 2 | R24: 11 | S24: 1
P25: 1 | Q25: 2 | R25: 12 | S25: 1
P26: 2 | Q26: 1 | R26: 1 | S26: 1
P27: 2 | Q27: 1 | R27: 2 | S27: 1
P28: 2 | Q28: 1 | R28: 3 | S28: 1
P29: 2 | Q29: 1 | R29: 4 | S29: 1
... P193: 7 | Q193: 2 | R193: 12 | S193: 1

Sheet PAR PI
A1: Coluna1 | B1: Coluna2 | C1: T_01 | D1: T_02 | E1: T_03 | F1: T_04 | G1: T_05 | H1: T_06 | I1: T_07 | J1: T_08 | K1: T_09 | L1: T_10 | M1: T_11 | N1: T_12 | P1: I | Q1: C | R1: T | S1: PI
A2: I_MAO. | B2: C_01 | C2: 0 | D2: 0 | E2: 0 | F2: 0 | G2: 0 | H2: 0 | I2: 0 | J2: 0 | K2: 0 | L2: 0 | M2: 0 | N2: 0 | P2: 1 | Q2: 1 | R2: 1 | S2: 0
A3: I_MAO. | B3: C_02 | C3: 0 | D3: 0 | E3: 0 | F3: 0 | G3: 0 | H3: 0 | I3: 0 | J3: 0 | K3: 0 | L3: 0 | M3: 0 | N3: 0 | P3: 1 | Q3: 1 | R3: 2 | S3: 0
A4: I_PEC. | B4: C_01 | C4: 0 | D4: 0 | E4: 0 | F4: 0 | G4: 0 | H4: 0 | I4: 0 | J4: 0 | K4: 0 | L4: 0 | M4: 0 | N4: 0 | P4: 1 | Q4: 1 | R4: 3 | S4: 0
A5: I_PEC. | B5: C_02 | C5: 0 | D5: 0 | E5: 0 | F5: 0 | G5: 0 | H5: 0 | I5: 0 | J5: 0 | K5: 0 | L5: 0 | M5: 0 | N5: 0 | P5: 1 | Q5: 1 | R5: 4 | S5: 0
A6: I_SUA. | B6: C_01 | C6: 0 | D6: 0 | E6: 0 | F6: 0 | G6: 0 | H6: 0 | I6: 0 | J6: 0 | K6: 0 | L6: 0 | M6: 0 | N6: 0 | P6: 1 | Q6: 1 | R6: 5 | S6: 0
A7: I_SUA. | B7: C_02 | C7: 0 | D7: 0 | E7: 0 | F7: 0 | G7: 0 | H7: 0 | I7: 0 | J7: 0 | K7: 0 | L7: 0 | M7: 0 | N7: 0 | P7: 1 | Q7: 1 | R7: 6 | S7: 0
A8: I_SSA. | B8: C_01 | C8: 0 | D8: 0 | E8: 0 | F8: 0 | G8: 0 | H8: 0 | I8: 0 | J8: 0 | K8: 0 | L8: 0 | M8: 0 | N8: 0 | P8: 1 | Q8: 1 | R8: 7 | S8: 0
A9: I_SSA. | B9: C_02 | C9: 0 | D9: 0 | E9: 0 | F9: 0 | G9: 0 | H9: 0 | I9: 0 | J9: 0 | K9: 0 | L9: 0 | M9: 0 | N9: 0 | P9: 1 | Q9: 1 | R9: 8 | S9: 0
A10: I_IGI. | B10: C_01 | C10: 0 | D10: 0 | E10: 0 | F10: 0 | G10: 0 | H10: 0 | I10: 0 | J10: 0 | K10: 0 | L10: 0 | M10: 0 | N10: 0 | P10: 1 | Q10: 1 | R10: 9 | S10: 0
A11: I_IGI. | B11: C_02 | C11: 0 | D11: 0 | E11: 0 | F11: 0 | G11: 0 | H11: 0 | I11: 0 | J11: 0 | K11: 0 | L11: 0 | M11: 0 | N11: 0 | P11: 1 | Q11: 1 | R11: 10 | S11: 0
A12: I_SSZ. | B12: C_01 | C12: 0 | D12: 0 | E12: 0 | F12: 0 | G12: 0 | H12: 0 | I12: 0 | J12: 0 | K12: 0 | L12: 0 | M12: 0 | N12: 0 | P12: 1 | Q12: 1 | R12: 11 | S12: 0
A13: I_SSZ. | B13: C_02 | C13: 0 | D13: 0 | E13: 0 | F13: 0 | G13: 0 | H13: 0 | I13: 0 | J13: 0 | K13: 0 | L13: 0 | M13: 0 | N13: 0 | P13: 1 | Q13: 1 | R13: 12 | S13: 0
... A17: I_IOA. | B17: C_02 | C17: 0 | D17: 0 | E17: 0 | F17: 0 | G17: 0 | H17: 0 | I17: 0 | J17: 0 | K17: 0 | L17: 0 | M17: 0 | N17: 0 | P17: 1 | Q17: 2 | R17: 4 | S17: 0
P18: 1 | Q18: 2 | R18: 5 | S18: 0
P19: 1 | Q19: 2 | R19: 6 | S19: 0
P20: 1 | Q20: 2 | R20: 7 | S20: 0
P21: 1 | Q21: 2 | R21: 8 | S21: 0
P22: 1 | Q22: 2 | R22: 9 | S22: 0
P23: 1 | Q23: 2 | R23: 10 | S23: 0
P24: 1 | Q24: 2 | R24: 11 | S24: 0
P25: 1 | Q25: 2 | R25: 12 | S25: 0
P26: 2 | Q26: 1 | R26: 1 | S26: 0
P27: 2 | Q27: 1 | R27: 2 | S27: 0
P28: 2 | Q28: 1 | R28: 3 | S28: 0
P29: 2 | Q29: 1 | R29: 4 | S29: 0
... P193: 7 | Q193: 2 | R193: 12 | S193: 0

Sheet PAR SF
A1: Coluna1 | B1: Coluna2 | C1: DT_0 | D1: DT_1 | E1: DT_2 | F1: DT_3 | H1: I | I1: K | J1: DT | K1: SF
A2: I_MAO. | B2: K20_D | C2: 0.6 | D2: 0.4 | E2: 0 | F2: 0 | H2: 1 | I2: 3 | J2: 0 | K2: 1
A3: I_MAO. | B3: K20_R | C3: 0.6 | D3: 0.4 | E3: 0 | F3: 0 | H3: 1 | I3: 3 | J3: 1 | K3: 0
A4: I_MAO. | B4: K40_D | C4: 0.6 | D4: 0.4 | E4: 0 | F4: 0 | H4: 1 | I4: 3 | J4: 2 | K4: 0
A5: I_MAO. | B5: K40_R | C5: 0.6 | D5: 0.4 | E5: 0 | F5: 0 | H5: 1 | I5: 3 | J5: 3 | K5: 0
A6: I_PEC. | B6: K20_D | C6: 0.6 | D6: 0.4 | E6: 0 | F6: 0 | H6: 1 | I6: 4 | J6: 0 | K6: 1
A7: I_PEC. | B7: K20_R | C7: 0.6 | D7: 0.4 | E7: 0 | F7: 0 | H7: 1 | I7: 4 | J7: 1 | K7: 0
A8: I_PEC. | B8: K40_D | C8: 0.6 | D8: 0.4 | E8: 0 | F8: 0 | H8: 1 | I8: 4 | J8: 2 | K8: 0
A9: I_PEC. | B9: K40_R | C9: 0.6 | D9: 0.4 | E9: 0 | F9: 0 | H9: 1 | I9: 4 | J9: 3 | K9: 0
A10: I_SUA. | B10: K20_D | C10: 0.6 | D10: 0.4 | E10: 0 | F10: 0 | H10: 1 | I10: 1 | J10: 0 | K10: 1
A11: I_SUA. | B11: K20_R | C11: 0.6 | D11: 0.4 | E11: 0 | F11: 0 | H11: 1 | I11: 1 | J11: 1 | K11: 0
A12: I_SUA. | B12: K40_D | C12: 0.6 | D12: 0.4 | E12: 0 | F12: 0 | H12: 1 | I12: 1 | J12: 2 | K12: 0
A13: I_SUA. | B13: K40_R | C13: 0.6 | D13: 0.4 | E13: 0 | F13: 0 | H13: 1 | I13: 1 | J13: 3 | K13: 0
... A33: I_IOA. | B33: K40_R | C33: 0.6 | D33: 0.4 | E33: 0 | F33: 0 | H33: 2 | I33: 2 | J33: 3 | K33: 0
H34: 3 | I34: 3 | J34: 0 | K34: 1
H35: 3 | I35: 3 | J35: 1 | K35: 0
H36: 3 | I36: 3 | J36: 2 | K36: 0
H37: 3 | I37: 3 | J37: 3 | K37: 0
H38: 3 | I38: 4 | J38: 0 | K38: 1
H39: 3 | I39: 4 | J39: 1 | K39: 0
H40: 3 | I40: 4 | J40: 2 | K40: 0
H41: 3 | I41: 4 | J41: 3 | K41: 0
H42: 3 | I42: 1 | J42: 0 | K42: 1
H43: 3 | I43: 1 | J43: 1 | K43: 0
H44: 3 | I44: 1 | J44: 2 | K44: 0
H45: 3 | I45: 1 | J45: 3 | K45: 0
... H129: 7 | I129: 2 | J129: 3 | K129: 0

Sheet PAR SE
A1: Coluna1 | B1: DT_0 | C1: DT_1 | D1: DT_2 | E1: DT_3 | G1: K | H1: DT | I1: SE
A2: K20_D | B2: 0.9 | C2: 0.1 | D2: 0 | E2: 0 | G2: 3 | H2: 0 | I2: 1
A3: K20_R | B3: 0.9 | C3: 0.1 | D3: 0 | E3: 0 | G3: 3 | H3: 1 | I3: 0
A4: K40_D | B4: 0.9 | C4: 0.1 | D4: 0 | E4: 0 | G4: 3 | H4: 2 | I4: 0
A5: K40_R | B5: 0.9 | C5: 0.1 | D5: 0 | E5: 0 | G5: 3 | H5: 3 | I5: 0
G6: 4 | H6: 0 | I6: 1
G7: 4 | H7: 1 | I7: 0
G8: 4 | H8: 2 | I8: 0
G9: 4 | H9: 3 | I9: 0
G10: 1 | H10: 0 | I10: 1
G11: 1 | H11: 1 | I11: 0
G12: 1 | H12: 2 | I12: 0
G13: 1 | H13: 3 | I13: 0
G14: 2 | H14: 0 | I14: 1
G15: 2 | H15: 1 | I15: 0
G16: 2 | H16: 2 | I16: 0
G17: 2 | H17: 3 | I17: 0

Sheet PAR H
A1: H('SB_MAO')= | B1: 45372.211 | C1: ; | F1: P | G1: H
A2: H('SB_PEC')= | B2: 45372.211 | C2: ; | F2: 1 | G2: 45372.211
A3: H('SB_SUA')= | B3: 45372.211 | C3: ; | F3: 2 | G3: 45372.211
A4: H('SB_SSA')= | B4: 45372.211 | C4: ; | F4: 3 | G4: 45372.211
A5: H('SB_IGI')= | B5: 45372.211 | C5: ; | F5: 4 | G5: 45372.211
A6: H('SB_SSZ')= | B6: 45372.211 | C6: ; | F6: 5 | G6: 45372.211
A7: H('SB_PNG')= | B7: 45372.211 | C7: ; | F7: 6 | G7: 45372.211
A8: H('SB_IOA')= | B8: 45372.211 | C8: ; | F8: 7 | G8: 45372.211
A9: H('NB_MAO')= | B9: 45372.211 | C9: ; | F9: 8 | G9: 45372.211
A10: H('NB_PEC')= | B10: 45372.211 | C10: ; | F10: 9 | G10: 45372.211
A11: H('NB_SUA')= | B11: 45372.211 | C11: ; | F11: 10 | G11: 45372.211
A12: H('NB_SSA')= | B12: 45372.211 | C12: ; | F12: 11 | G12: 45372.211
A13: H('NB_IGI')= | B13: 45372.211 | C13: ; | F13: 12 | G13: 45372.211
... A16: H('NB_IOA')= | B16: 45372.211 | C16: ; | F16: 15 | G16: 45372.211
F17: 16 | G17: 45372.211

Sheet PAR NV
A1: VV = | B1: 4 | C1: ;

Sheet PAR VC
A1: VC = | B1: 0.93 | C1: ;

Sheet PAR DP
A1: I | B1: J | C1: DP
A2: 8 | B2: 9 | C2: 104
A3: 9 | B3: 8 | C3: 104
A4: 6 | B4: 8 | C4: 167
A5: 8 | B5: 6 | C5: 167
A6: 6 | B6: 13 | C6: 219
A7: 13 | B7: 6 | C7: 219
A8: 6 | B8: 9 | C8: 226
A9: 9 | B9: 6 | C9: 226
A10: 12 | B10: 13 | C10: 281
A11: 13 | B11: 12 | C11: 281
A12: 8 | B12: 13 | C12: 349
A13: 13 | B13: 8 | C13: 349
... A102: 1 | B102: 16 | C102: 3834

Sheet PAR DCID
A1: I | B1: J | C1: DCID
A2: 8 | B2: 9 | C2: 131
A3: 9 | B3: 8 | C3: 131
A4: 6 | B4: 8 | C4: 408
A5: 8 | B5: 6 | C5: 408
A6: 13 | B6: 6 | C6: 429
A7: 6 | B7: 13 | C7: 429
A8: 12 | B8: 13 | C8: 521
A9: 13 | B9: 12 | C9: 521
A10: 9 | B10: 16 | C10: 618
A11: 16 | B11: 9 | C11: 618
A12: 6 | B12: 9 | C12: 624
A13: 9 | B13: 6 | C13: 624
... A91: 16 | B91: 10 | C91: 4397

Sheet PAR CSC
A1: I | B1: NT | C1: CSC
A2: 1 | B2: 3500 | C2: 745042
A3: 1 | B3: 3000 | C3: 722691
A4: 1 | B4: 2500 | C4: 707790
A5: 1 | B5: 2000 | C5: 670538
A6: 10 | B6: 3500 | C6: 102000
A7: 10 | B7: 3000 | C7: 98940
A8: 10 | B8: 2500 | C8: 96900
A9: 10 | B9: 2000 | C9: 91800
A10: 2 | B10: 3500 | C10: 102000
A11: 2 | B11: 3000 | C11: 98940
A12: 2 | B12: 2500 | C12: 96900
A13: 2 | B13: 2000 | C13: 91800
... A61: 16 | B61: 2000 | C61: 112320

Sheet PAR DEPOTS
A1: Porto | B1: Distância Capital
A2: 1 | B2: 10
A3: 10 | B3: 115
A4: 11 | B4: 15
A5: 2 | B5: 60
A6: 3 | B6: 51
A7: 4 | B7: 10
A8: 12 | B8: 12
A9: 13 | B9: 10
A10: 6 | B10: 100
A11: 8 | B11: 95
A12: 7 | B12: 258
A13: 16 | B13: 320

Sheet PAR 20X40
A1: 20/40 RF
A2: 0.8

Sheet PAR MAO-VLC
A1: Item | B1: Valor | C1: Unidade
A2: Custo Balsa | B2: 10000 | C2: BRL/Veículo
A3: Margem de Lucro | B3: 0 | C3: %
A4: ID VLC | B4: 10 | C4: -

Sheet PAR INTERMODAL
A1: PARAMETER | B1: DRY | C1: REEFER | D1: UNIT
A2: Axels | B2: 6 | C2: 6 | D2: -
A3: Cost Coeficient | B3: 5.6748 | C3: 6.0043 | D3: BRL/km
A4: Load/Discharge Cost | B4: 496.5 | C4: 597.42 | D4: BRL
A5: Margin | B5: 0.15 | C5: 0.15 | D5: -
A6: Fator Extra Intermodal | B6: 0.3 | C6: 0.3 | D6: -
B9: =1-B5 -> 0.85

Sheet PAR TM
A1: I | B1: TM
A2: 1 | B2: 0.0011904762
A3: 10 | B3: 0.0016666667
A4: 11 | B4: 0.0016666667
A5: 2 | B5: 0.0010416667
A6: 3 | B6: 0.00092592593
A7: 4 | B7: 0.00083333333
A8: 12 | B8: 0.0011904762
A9: 5 | B9: 0.00083333333
A10: 13 | B10: 0.00083333333
A11: 6 | B11: 0.00083333333
A12: 8 | B12: 0.00083333333
A13: 7 | B13: 0.00083333333
... A17: 16 | B17: 0.00083333333

Sheet PAR TO
A1: I | B1: TO
A2: 1 | B2: 0.25
A3: 10 | B3: 0.33333333
A4: 11 | B4: 0.33333333
A5: 2 | B5: 0.20833333
A6: 3 | B6: 0.20833333
A7: 4 | B7: 0.20833333
A8: 12 | B8: 0.25
A9: 5 | B9: 0.33333333
A10: 13 | B10: 0.25
A11: 6 | B11: 0.25
A12: 8 | B12: 0.25
A13: 7 | B13: 0.25
... A17: 16 | B17: 0.25

Sheet PAR FUEL
A1: Combustível | B1: Preço | C1: Unidade
A2: VLSFO | B2: 641 | C2: USD/t
A3: MDO | B3: 932.5 | C3: USD/t

Sheet PAR MC
A1: MDO Consumption | B1: t/day
A2: Sea | B2: 3.5
A3: Port | B3: 5

Sheet PAR USD
A1: Item | B1: Valor | C1: Unidade
A2: Taxa de Câmbio | B2: 5.48 | C2: BRL/USD

Sheet PAR NT
A1: VT= | B1: 3500 | C1: ;

Sheet PAR ND
A1: NT | B1: ND
A2: 2000 | B2: 22400
A3: 2500 | B3: 28000
A4: 3000 | B4: 33600
A5: 3500 | B5: 39200

Sheet PAR NP
A1: NP = | B1: 500 | C1: ;

Sheet PAR NF
A1: NF = | B1: 1710 | C1: ;

Sheet PAR NE
A1: NE('I_MAO')= | B1: 3000 | C1: ; | D1: I | E1: NE
A2: NE('I_PEC')= | B2: 3000 | C2: ; | D2: 1 | E2: 3000
A3: NE('I_SUA')= | B3: 3000 | C3: ; | D3: 2 | E3: 3000
A4: NE('I_SSA')= | B4: 3000 | C4: ; | D4: 3 | E4: 3000
A5: NE('I_IGI')= | B5: 3000 | C5: ; | D5: 4 | E5: 3000
A6: NE('I_SSZ')= | B6: 5000 | C6: ; | D6: 5 | E6: 3000
A7: NE('I_PNG')= | B7: 3000 | C7: ; | D7: 6 | E7: 5000
A8: NE('I_IOA')= | B8: 3000 | C8: ; | D8: 8 | E8: 3000
D9: 7 | E9: 3000
A11: =LEFT(RIGHT(A1,8),5) -> I_MAO
A12: =LEFT(RIGHT(A2,8),5) -> I_PEC
A13: =LEFT(RIGHT(A3,8),5) -> I_SUA
A14: =LEFT(RIGHT(A4,8),5) -> I_SSA
A15: =LEFT(RIGHT(A5,8),5) -> I_IGI
A16: =LEFT(RIGHT(A6,8),5) -> I_SSZ
A17: =LEFT(RIGHT(A7,8),5) -> I_PNG
A18: =LEFT(RIGHT(A8,8),5) -> I_IOA

Sheet PAR NC
A1: NC('K20_D')= | B1: 50000 | C1: ; | D1: K | E1: NC
A2: NC('K20_R')= | B2: 50000 | C2: ; | D2: 3 | E2: 50000
A3: NC('K40_D')= | B3: 50000 | C3: ; | D3: 4 | E3: 50000
A4: NC('K40_R')= | B4: 50000 | C4: ; | D4: 1 | E4: 50000
D5: 2 | E5: 50000
A8: =LEFT(RIGHT(A1,8),5) -> K20_D
A9: =LEFT(RIGHT(A2,8),5) -> K20_R
A10: =LEFT(RIGHT(A3,8),5) -> K40_D
A11: =LEFT(RIGHT(A4,8),5) -> K40_R

Sheet PAR G
A1: K | B1: G
A2: 1 | B2: 0
A3: 2 | B3: 1
A4: 3 | B4: 0
A5: 4 | B5: 1
A7: 1->reefer; 0->dry

Sheet PAR Q
A1: K | B1: Q
A2: 1 | B2: 2
A3: 2 | B3: 2
A4: 3 | B4: 1
A5: 4 | B5: 1
A7: 1->20 pés; 2->40 pés
